Workbook

Sheet Dashboard
A1: Options Income Dashboard
A2: High-level view across realized P/L, strategy buckets, current portfolio weight, and open option exposure.
A4: YTD Realized P/L | B4: =SUM('Trade Log'!$R$5:$R$1004) | D4: Avg Monthly P/L | E4: =IFERROR(AVERAGEIF('Revenue Tracker'!$G$5:$G$28,"<>0",'Revenue Tracker'!$G$5:$G$28),0) | G4: Portfolio Value | H4: =SUM(Portfolio!$E$5:$E$154)
A7: Open CSP Collateral | B7: =SUMIFS('Trade Log'!$T$5:$T$1004,'Trade Log'!$B$5:$B$1004,"Cash Secured Put",'Trade Log'!$C$5:$C$1004,"Open") | D7: Open CC Contracts | E7: =SUMIFS('Trade Log'!$M$5:$M$1004,'Trade Log'!$B$5:$B$1004,"Covered Call",'Trade Log'!$C$5:$C$1004,"Open") | G7: Closed Trade Count | H7: =COUNTIF('Trade Log'!$C$5:$C$1004,"Closed")
A11: Recent Monthly Performance
A12: ='Revenue Tracker'!A5 | B12: ='Revenue Tracker'!B5 | C12: ='Revenue Tracker'!C5 | D12: ='Revenue Tracker'!D5 | E12: ='Revenue Tracker'!E5 | F12: ='Revenue Tracker'!F5 | G12: ='Revenue Tracker'!G5 | H12: ='Revenue Tracker'!H5 | I12: ='Revenue Tracker'!I5
A13: ='Revenue Tracker'!A6 | B13: ='Revenue Tracker'!B6 | C13: ='Revenue Tracker'!C6 | D13: ='Revenue Tracker'!D6 | E13: ='Revenue Tracker'!E6 | F13: ='Revenue Tracker'!F6 | G13: ='Revenue Tracker'!G6 | H13: ='Revenue Tracker'!H6 | I13: ='Revenue Tracker'!I6
A14: ='Revenue Tracker'!A7 | B14: ='Revenue Tracker'!B7 | C14: ='Revenue Tracker'!C7 | D14: ='Revenue Tracker'!D7 | E14: ='Revenue Tracker'!E7 | F14: ='Revenue Tracker'!F7 | G14: ='Revenue Tracker'!G7 | H14: ='Revenue Tracker'!H7 | I14: ='Revenue Tracker'!I7
A15: ='Revenue Tracker'!A8 | B15: ='Revenue Tracker'!B8 | C15: ='Revenue Tracker'!C8 | D15: ='Revenue Tracker'!D8 | E15: ='Revenue Tracker'!E8 | F15: ='Revenue Tracker'!F8 | G15: ='Revenue Tracker'!G8 | H15: ='Revenue Tracker'!H8 | I15: ='Revenue Tracker'!I8
A16: ='Revenue Tracker'!A9 | B16: ='Revenue Tracker'!B9 | C16: ='Revenue Tracker'!C9 | D16: ='Revenue Tracker'!D9 | E16: ='Revenue Tracker'!E9 | F16: ='Revenue Tracker'!F9 | G16: ='Revenue Tracker'!G9 | H16: ='Revenue Tracker'!H9 | I16: ='Revenue Tracker'!I9
A17: ='Revenue Tracker'!A10 | B17: ='Revenue Tracker'!B10 | C17: ='Revenue Tracker'!C10 | D17: ='Revenue Tracker'!D10 | E17: ='Revenue Tracker'!E10 | F17: ='Revenue Tracker'!F10 | G17: ='Revenue Tracker'!G10 | H17: ='Revenue Tracker'!H10 | I17: ='Revenue Tracker'!I10

Sheet How to Use
A1: How to Use This Tracker
A2: Designed for a Google Sheets or Excel workflow: one trade row, formula summaries, manual current positions, and a running idea log.
A4: 1. Log each trade
A5: Use Trade Log for options and stock trades. Fill the blue input columns: strategy, status, open/close dates, ticker, asset/action, option type, strike, expiration, quantity, entry price, close price, fees, and notes. The realized P/L, category, collateral/notional, and annualized return columns calculate automatically.
A8: 2. Review monthly income
A9: Revenue Tracker rolls closed trades into monthly buckets: covered call premiums, cash secured put premiums, long option/spread P/L, stock sales, and other. The ticker summary underneath shows which symbols are producing or losing money.
A12: 3. Maintain portfolio weights
A13: Portfolio is intentionally manual for current shares, prices, and average cost. Enter current broker balances there; market value, weight, unrealized P/L, open covered calls, open short puts, and cash-secured obligation update from formulas.
A16: 4. Train future recommendations
A17: Use Trade Ideas to capture sample setups, combinations, thesis, max profit/loss, result, and lessons. Over time, this becomes the preference file for what kinds of option structures you like, avoid, or want me to compare.
A20: 5. Updating with Codex
A21: You can paste trade confirmations, broker export rows, or plain-English trade notes and ask me to append them. Best input format is: date, ticker, strategy, buy/sell, call/put, strike, expiration, quantity, entry/exit price, fees, status, and any assignment/roll notes.

Sheet Trade Log
A1: Options & Stock Trade Log
A2: One row per trade. Blue columns are the usual inputs; calculated P/L, category, collateral, and annualized return update from the row.
A4: Trade ID | B4: Strategy | C4: Status | D4: Open Date | E4: Close Date | F4: Realization Month | G4: Ticker | H4: Asset | I4: Action | J4: Option Type | K4: Strike | L4: Expiration | M4: Qty | N4: Entry Price | O4: Exit/Close Price | P4: Fees | Q4: Trade P/L / Cash Flow | R4: Realized P/L | S4: Revenue Category | T4: Collateral / Notional | U4: Annualized Return | V4: Notes | W4: Source
A5: 1 | B5: Covered Call | C5: Closed | D5: 46136 | E5: 46168 | F5: =IF($E5="","",DATE(YEAR($E5),MONTH($E5),1)) | G5: BMNR | H5: Option | I5: Sell | J5: Call | K5: 26.5 | L5: 46178 | M5: 1 | N5: 1.06 | O5: 0.1 | P5: 0.04 | Q5: =IF($A5="","",IF($H5="Stock",IF($I5="Buy",-$M5*$N5-$P5,IF($I5="Sell",IF($N5="", $M5*$O5-$P5,($O5-$N5)*$M5-$P5),"")),IF($I5="Sell",($N5-IF($O5="",0,$O5))*$M5*100-$P5,IF($I5="Buy",(IF($O5="",0,$O5)-$N5)*$M5*100-$P5,"")))) | R5: =IF($A5="","",IF($C5="Open","",$Q5)) | S5: =IF($A5="","",IFS($B5="Covered Call","Covered Call Premium",$B5="Cash Secured Put","Cash Secured Put Premium",$B5="Long Call/Put","Long Call/Put P/L",$B5="Debit Spread","Long Call/Put P/L",$B5="Stock Sale","Stock Sales",TRUE,"Other")) | T5: =IF($A5="","",IF($B5="Cash Secured Put",$K5*$M5*100,IF($B5="Covered Call",$K5*$M5*100,IF($H5="Stock",$M5*$N5,"")))) | U5: =IF(OR($A5="",$C5<>"Closed",$D5="",$E5="",$T5=0),"",$R5/$T5*365/MAX(1,$E5-$D5)) | V5: Bought to close per individual CSV. | W5: Broker CSV
A6: 2 | B6: Cash Secured Put | C6: Open | D6: 46156 | F6: =IF($E6="","",DATE(YEAR($E6),MONTH($E6),1)) | G6: LUMN | H6: Option | I6: Sell | J6: Put | K6: 11 | L6: 46185 | M6: 1 | N6: 1.02 | O6: 1.35 | P6: 0 | Q6: =IF($A6="","",IF($H6="Stock",IF($I6="Buy",-$M6*$N6-$P6,IF($I6="Sell",IF($N6="", $M6*$O6-$P6,($O6-$N6)*$M6-$P6),"")),IF($I6="Sell",($N6-IF($O6="",0,$O6))*$M6*100-$P6,IF($I6="Buy",(IF($O6="",0,$O6)-$N6)*$M6*100-$P6,"")))) | R6: =IF($A6="","",IF($C6="Open","",$Q6)) | S6: =IF($A6="","",IFS($B6="Covered Call","Covered Call Premium",$B6="Cash Secured Put","Cash Secured Put Premium",$B6="Long Call/Put","Long Call/Put P/L",$B6="Debit Spread","Long Call/Put P/L",$B6="Stock Sale","Stock Sales",TRUE,"Other")) | T6: =IF($A6="","",IF($B6="Cash Secured Put",$K6*$M6*100,IF($B6="Covered Call",$K6*$M6*100,IF($H6="Stock",$M6*$N6,"")))) | U6: =IF(OR($A6="",$C6<>"Closed",$D6="",$E6="",$T6=0),"",$R6/$T6*365/MAX(1,$E6-$D6)) | V6: Open position retained from tracker; not present in YTD CSV exports. | W6: Existing tracker
A7: 3 | B7: Cash Secured Put | C7: Closed | D7: 46136 | E7: 46170 | F7: =IF($E7="","",DATE(YEAR($E7),MONTH($E7),1)) | G7: SOFI | H7: Option | I7: Sell | J7: Put | K7: 17 | L7: 46178 | M7: 1 | N7: 0.91 | O7: 0.54 | P7: 0.04 | Q7: =IF($A7="","",IF($H7="Stock",IF($I7="Buy",-$M7*$N7-$P7,IF($I7="Sell",IF($N7="", $M7*$O7-$P7,($O7-$N7)*$M7-$P7),"")),IF($I7="Sell",($N7-IF($O7="",0,$O7))*$M7*100-$P7,IF($I7="Buy",(IF($O7="",0,$O7)-$N7)*$M7*100-$P7,"")))) | R7: =IF($A7="","",IF($C7="Open","",$Q7)) | S7: =IF($A7="","",IFS($B7="Covered Call","Covered Call Premium",$B7="Cash Secured Put","Cash Secured Put Premium",$B7="Long Call/Put","Long Call/Put P/L",$B7="Debit Spread","Long Call/Put P/L",$B7="Stock Sale","Stock Sales",TRUE,"Other")) | T7: =IF($A7="","",IF($B7="Cash Secured Put",$K7*$M7*100,IF($B7="Covered Call",$K7*$M7*100,IF($H7="Stock",$M7*$N7,"")))) | U7: =IF(OR($A7="",$C7<>"Closed",$D7="",$E7="",$T7=0),"",$R7/$T7*365/MAX(1,$E7-$D7)) | V7: Bought to close per joint CSV. | W7: Broker CSV
A8: 4 | B8: Covered Call | C8: Closed | D8: 46147 | E8: 46160 | F8: =IF($E8="","",DATE(YEAR($E8),MONTH($E8),1)) | G8: PLTR | H8: Option | I8: Sell | J8: Call | K8: 150 | L8: 46178 | M8: 1 | N8: 3.55 | O8: 1.16 | P8: 0.04 | Q8: =IF($A8="","",IF($H8="Stock",IF($I8="Buy",-$M8*$N8-$P8,IF($I8="Sell",IF($N8="", $M8*$O8-$P8,($O8-$N8)*$M8-$P8),"")),IF($I8="Sell",($N8-IF($O8="",0,$O8))*$M8*100-$P8,IF($I8="Buy",(IF($O8="",0,$O8)-$N8)*$M8*100-$P8,"")))) | R8: =IF($A8="","",IF($C8="Open","",$Q8)) | S8: =IF($A8="","",IFS($B8="Covered Call","Covered Call Premium",$B8="Cash Secured Put","Cash Secured Put Premium",$B8="Long Call/Put","Long Call/Put P/L",$B8="Debit Spread","Long Call/Put P/L",$B8="Stock Sale","Stock Sales",TRUE,"Other")) | T8: =IF($A8="","",IF($B8="Cash Secured Put",$K8*$M8*100,IF($B8="Covered Call",$K8*$M8*100,IF($H8="Stock",$M8*$N8,"")))) | U8: =IF(OR($A8="",$C8<>"Closed",$D8="",$E8="",$T8=0),"",$R8/$T8*365/MAX(1,$E8-$D8)) | V8: Bought to close per joint CSV. | W8: Broker CSV
A9: 5 | B9: Covered Call | C9: Closed | D9: 46148 | E9: 46170 | F9: =IF($E9="","",DATE(YEAR($E9),MONTH($E9),1)) | G9: PLTR | H9: Option | I9: Sell | J9: Call | K9: 160 | L9: 46178 | M9: 1 | N9: 1.45 | O9: 0.21 | P9: 0.04 | Q9: =IF($A9="","",IF($H9="Stock",IF($I9="Buy",-$M9*$N9-$P9,IF($I9="Sell",IF($N9="", $M9*$O9-$P9,($O9-$N9)*$M9-$P9),"")),IF($I9="Sell",($N9-IF($O9="",0,$O9))*$M9*100-$P9,IF($I9="Buy",(IF($O9="",0,$O9)-$N9)*$M9*100-$P9,"")))) | R9: =IF($A9="","",IF($C9="Open","",$Q9)) | S9: =IF($A9="","",IFS($B9="Covered Call","Covered Call Premium",$B9="Cash Secured Put","Cash Secured Put Premium",$B9="Long Call/Put","Long Call/Put P/L",$B9="Debit Spread","Long Call/Put P/L",$B9="Stock Sale","Stock Sales",TRUE,"Other")) | T9: =IF($A9="","",IF($B9="Cash Secured Put",$K9*$M9*100,IF($B9="Covered Call",$K9*$M9*100,IF($H9="Stock",$M9*$N9,"")))) | U9: =IF(OR($A9="",$C9<>"Closed",$D9="",$E9="",$T9=0),"",$R9/$T9*365/MAX(1,$E9-$D9)) | V9: Bought to close per joint CSV. | W9: Broker CSV
A10: 6 | B10: Covered Call | C10: Closed | D10: 46153 | E10: 46178 | F10: =IF($E10="","",DATE(YEAR($E10),MONTH($E10),1)) | G10: PLTR | H10: Option | I10: Sell | J10: Call | K10: 175 | L10: 46178 | M10: 1 | N10: 0.49 | O10: 0 | P10: 0 | Q10: =IF($A10="","",IF($H10="Stock",IF($I10="Buy",-$M10*$N10-$P10,IF($I10="Sell",IF($N10="", $M10*$O10-$P10,($O10-$N10)*$M10-$P10),"")),IF($I10="Sell",($N10-IF($O10="",0,$O10))*$M10*100-$P10,IF($I10="Buy",(IF($O10="",0,$O10)-$N10)*$M10*100-$P10,"")))) | R10: =IF($A10="","",IF($C10="Open","",$Q10)) | S10: =IF($A10="","",IFS($B10="Covered Call","Covered Call Premium",$B10="Cash Secured Put","Cash Secured Put Premium",$B10="Long Call/Put","Long Call/Put P/L",$B10="Debit Spread","Long Call/Put P/L",$B10="Stock Sale","Stock Sales",TRUE,"Other")) | T10: =IF($A10="","",IF($B10="Cash Secured Put",$K10*$M10*100,IF($B10="Covered Call",$K10*$M10*100,IF($H10="Stock",$M10*$N10,"")))) | U10: =IF(OR($A10="",$C10<>"Closed",$D10="",$E10="",$T10=0),"",$R10/$T10*365/MAX(1,$E10-$D10)) | V10: Expired per joint CSV option expiration row. | W10: Broker CSV
A11: 7 | B11: Covered Call | C11: Closed | D11: 46146 | E11: 46168 | F11: =IF($E11="","",DATE(YEAR($E11),MONTH($E11),1)) | G11: PLTR | H11: Option | I11: Sell | J11: Call | K11: 220 | L11: 46178 | M11: 1 | N11: 0.44 | O11: 0.03 | P11: 0.04 | Q11: =IF($A11="","",IF($H11="Stock",IF($I11="Buy",-$M11*$N11-$P11,IF($I11="Sell",IF($N11="", $M11*$O11-$P11,($O11-$N11)*$M11-$P11),"")),IF($I11="Sell",($N11-IF($O11="",0,$O11))*$M11*100-$P11,IF($I11="Buy",(IF($O11="",0,$O11)-$N11)*$M11*100-$P11,"")))) | R11: =IF($A11="","",IF($C11="Open","",$Q11)) | S11: =IF($A11="","",IFS($B11="Covered Call","Covered Call Premium",$B11="Cash Secured Put","Cash Secured Put Premium",$B11="Long Call/Put","Long Call/Put P/L",$B11="Debit Spread","Long Call/Put P/L",$B11="Stock Sale","Stock Sales",TRUE,"Other")) | T11: =IF($A11="","",IF($B11="Cash Secured Put",$K11*$M11*100,IF($B11="Covered Call",$K11*$M11*100,IF($H11="Stock",$M11*$N11,"")))) | U11: =IF(OR($A11="",$C11<>"Closed",$D11="",$E11="",$T11=0),"",$R11/$T11*365/MAX(1,$E11-$D11)) | V11: Bought to close per joint CSV. | W11: Broker CSV
A12: 8 | B12: Cash Secured Put | C12: Closed | D12: 46148 | E12: 46161 | F12: =IF($E12="","",DATE(YEAR($E12),MONTH($E12),1)) | G12: ASTS | H12: Option | I12: Sell | J12: Put | K12: 65 | L12: 46178 | M12: 1 | N12: 5.75 | O12: 1.5 | P12: 0.04 | Q12: =IF($A12="","",IF($H12="Stock",IF($I12="Buy",-$M12*$N12-$P12,IF($I12="Sell",IF($N12="", $M12*$O12-$P12,($O12-$N12)*$M12-$P12),"")),IF($I12="Sell",($N12-IF($O12="",0,$O12))*$M12*100-$P12,IF($I12="Buy",(IF($O12="",0,$O12)-$N12)*$M12*100-$P12,"")))) | R12: =IF($A12="","",IF($C12="Open","",$Q12)) | S12: =IF($A12="","",IFS($B12="Covered Call","Covered Call Premium",$B12="Cash Secured Put","Cash Secured Put Premium",$B12="Long Call/Put","Long Call/Put P/L",$B12="Debit Spread","Long Call/Put P/L",$B12="Stock Sale","Stock Sales",TRUE,"Other")) | T12: =IF($A12="","",IF($B12="Cash Secured Put",$K12*$M12*100,IF($B12="Covered Call",$K12*$M12*100,IF($H12="Stock",$M12*$N12,"")))) | U12: =IF(OR($A12="",$C12<>"Closed",$D12="",$E12="",$T12=0),"",$R12/$T12*365/MAX(1,$E12-$D12)) | V12: Bought to close per user/broker activity. | W12: Broker CSV
A13: 9 | B13: Cash Secured Put | C13: Closed | D13: 46146 | E13: 46157 | F13: =IF($E13="","",DATE(YEAR($E13),MONTH($E13),1)) | G13: NEXT | H13: Option | I13: Sell | J13: Put | K13: 8 | L13: 46157 | M13: 2 | N13: 0.33 | O13: 0 | P13: 0 | Q13: =IF($A13="","",IF($H13="Stock",IF($I13="Buy",-$M13*$N13-$P13,IF($I13="Sell",IF($N13="", $M13*$O13-$P13,($O13-$N13)*$M13-$P13),"")),IF($I13="Sell",($N13-IF($O13="",0,$O13))*$M13*100-$P13,IF($I13="Buy",(IF($O13="",0,$O13)-$N13)*$M13*100-$P13,"")))) | R13: =IF($A13="","",IF($C13="Open","",$Q13)) | S13: =IF($A13="","",IFS($B13="Covered Call","Covered Call Premium",$B13="Cash Secured Put","Cash Secured Put Premium",$B13="Long Call/Put","Long Call/Put P/L",$B13="Debit Spread","Long Call/Put P/L",$B13="Stock Sale","Stock Sales",TRUE,"Other")) | T13: =IF($A13="","",IF($B13="Cash Secured Put",$K13*$M13*100,IF($B13="Covered Call",$K13*$M13*100,IF($H13="Stock",$M13*$N13,"")))) | U13: =IF(OR($A13="",$C13<>"Closed",$D13="",$E13="",$T13=0),"",$R13/$T13*365/MAX(1,$E13-$D13)) | V13: Expired/closed after 2026-05-15 expiration; retained from tracker with CSV confirming no later close. | W13: Existing tracker + Broker CSV
A14: 10 | B14: Debit Spread | C14: Open | D14: 46051 | F14: =IF($E14="","",DATE(YEAR($E14),MONTH($E14),1)) | G14: GRAB | H14: Option Spread | I14: Buy | J14: Call | K14: 10 | L14: 46773 | M14: 180 | N14: 0.1 | O14: 0.08 | P14: 0 | Q14: =IF($A14="","",IF($H14="Stock",IF($I14="Buy",-$M14*$N14-$P14,IF($I14="Sell",IF($N14="", $M14*$O14-$P14,($O14-$N14)*$M14-$P14),"")),IF($I14="Sell",($N14-IF($O14="",0,$O14))*$M14*100-$P14,IF($I14="Buy",(IF($O14="",0,$O14)-$N14)*$M14*100-$P14,"")))) | R14: =IF($A14="","",IF($C14="Open","",$Q14)) | S14: =IF($A14="","",IFS($B14="Covered Call","Covered Call Premium",$B14="Cash Secured Put","Cash Secured Put Premium",$B14="Long Call/Put","Long Call/Put P/L",$B14="Debit Spread","Long Call/Put P/L",$B14="Stock Sale","Stock Sales",TRUE,"Other")) | T14: =IF($A14="","",IF($B14="Cash Secured Put",$K14*$M14*100,IF($B14="Covered Call",$K14*$M14*100,IF($H14="Stock",$M14*$N14,"")))) | U14: =IF(OR($A14="",$C14<>"Closed",$D14="",$E14="",$T14=0),"",$R14/$T14*365/MAX(1,$E14-$D14)) | V14: Open GRAB $10/$12 call debit spread; YTD CSV confirms 180 paired contracts. | W14: Broker CSV + existing tracker
A15: 11 | B15: Covered Call | C15: Open | D15: 46129 | F15: =IF($E15="","",DATE(YEAR($E15),MONTH($E15),1)) | G15: PLTR | H15: Option | I15: Sell | J15: Call | K15: 190 | L15: 46402 | M15: 1 | N15: 14.73 | O15: 9.38 | P15: 0 | Q15: =IF($A15="","",IF($H15="Stock",IF($I15="Buy",-$M15*$N15-$P15,IF($I15="Sell",IF($N15="", $M15*$O15-$P15,($O15-$N15)*$M15-$P15),"")),IF($I15="Sell",($N15-IF($O15="",0,$O15))*$M15*100-$P15,IF($I15="Buy",(IF($O15="",0,$O15)-$N15)*$M15*100-$P15,"")))) | R15: =IF($A15="","",IF($C15="Open","",$Q15)) | S15: =IF($A15="","",IFS($B15="Covered Call","Covered Call Premium",$B15="Cash Secured Put","Cash Secured Put Premium",$B15="Long Call/Put","Long Call/Put P/L",$B15="Debit Spread","Long Call/Put P/L",$B15="Stock Sale","Stock Sales",TRUE,"Other")) | T15: =IF($A15="","",IF($B15="Cash Secured Put",$K15*$M15*100,IF($B15="Covered Call",$K15*$M15*100,IF($H15="Stock",$M15*$N15,"")))) | U15: =IF(OR($A15="",$C15<>"Closed",$D15="",$E15="",$T15=0),"",$R15/$T15*365/MAX(1,$E15-$D15)) | V15: Open PLTR $190 covered call per individual CSV. | W15: Broker CSV
A16: 12 | B16: Debit Spread | C16: Open | D16: 45681 | F16: =IF($E16="","",DATE(YEAR($E16),MONTH($E16),1)) | G16: GRAB | H16: Option Spread | I16: Buy | J16: Call | K16: 7.5 | L16: 46402 | M16: 400 | N16: 0.29 | O16: 0.03 | P16: 0 | Q16: =IF($A16="","",IF($H16="Stock",IF($I16="Buy",-$M16*$N16-$P16,IF($I16="Sell",IF($N16="", $M16*$O16-$P16,($O16-$N16)*$M16-$P16),"")),IF($I16="Sell",($N16-IF($O16="",0,$O16))*$M16*100-$P16,IF($I16="Buy",(IF($O16="",0,$O16)-$N16)*$M16*100-$P16,"")))) | R16: =IF($A16="","",IF($C16="Open","",$Q16)) | S16: =IF($A16="","",IFS($B16="Covered Call","Covered Call Premium",$B16="Cash Secured Put","Cash Secured Put Premium",$B16="Long Call/Put","Long Call/Put P/L",$B16="Debit Spread","Long Call/Put P/L",$B16="Stock Sale","Stock Sales",TRUE,"Other")) | T16: =IF($A16="","",IF($B16="Cash Secured Put",$K16*$M16*100,IF($B16="Covered Call",$K16*$M16*100,IF($H16="Stock",$M16*$N16,"")))) | U16: =IF(OR($A16="",$C16<>"Closed",$D16="",$E16="",$T16=0),"",$R16/$T16*365/MAX(1,$E16-$D16)) | V16: Consolidated GRAB $7.50/$10 call debit spreads. Existing tracker keeps pre-2026 contracts; CSV confirms 60 YTD additions. | W16: Existing tracker + Broker CSV
A17: 13 | B17: Long Call/Put | C17: Open | D17: 45989 | F17: =IF($E17="","",DATE(YEAR($E17),MONTH($E17),1)) | G17: BMNR | H17: Option | I17: Buy | J17: Call | K17: 75 | L17: 46191 | M17: 1 | N17: 4.75 | O17: 0.02 | P17: 0 | Q17: =IF($A17="","",IF($H17="Stock",IF($I17="Buy",-$M17*$N17-$P17,IF($I17="Sell",IF($N17="", $M17*$O17-$P17,($O17-$N17)*$M17-$P17),"")),IF($I17="Sell",($N17-IF($O17="",0,$O17))*$M17*100-$P17,IF($I17="Buy",(IF($O17="",0,$O17)-$N17)*$M17*100-$P17,"")))) | R17: =IF($A17="","",IF($C17="Open","",$Q17)) | S17: =IF($A17="","",IFS($B17="Covered Call","Covered Call Premium",$B17="Cash Secured Put","Cash Secured Put Premium",$B17="Long Call/Put","Long Call/Put P/L",$B17="Debit Spread","Long Call/Put P/L",$B17="Stock Sale","Stock Sales",TRUE,"Other")) | T17: =IF($A17="","",IF($B17="Cash Secured Put",$K17*$M17*100,IF($B17="Covered Call",$K17*$M17*100,IF($H17="Stock",$M17*$N17,"")))) | U17: =IF(OR($A17="",$C17<>"Closed",$D17="",$E17="",$T17=0),"",$R17/$T17*365/MAX(1,$E17-$D17)) | V17: Long BMNR $75 call retained from tracker; opened before CSV period. | W17: Existing tracker
A18: 14 | B18: Covered Call | C18: Closed | D18: 46140 | E18: 46170 | F18: =IF($E18="","",DATE(YEAR($E18),MONTH($E18),1)) | G18: AEHR | H18: Option | I18: Sell | J18: Call | K18: 150 | L18: 46191 | M18: 1 | N18: 2.9 | O18: 2.78 | P18: 0.04 | Q18: =IF($A18="","",IF($H18="Stock",IF($I18="Buy",-$M18*$N18-$P18,IF($I18="Sell",IF($N18="", $M18*$O18-$P18,($O18-$N18)*$M18-$P18),"")),IF($I18="Sell",($N18-IF($O18="",0,$O18))*$M18*100-$P18,IF($I18="Buy",(IF($O18="",0,$O18)-$N18)*$M18*100-$P18,"")))) | R18: =IF($A18="","",IF($C18="Open","",$Q18)) | S18: =IF($A18="","",IFS($B18="Covered Call","Covered Call Premium",$B18="Cash Secured Put","Cash Secured Put Premium",$B18="Long Call/Put","Long Call/Put P/L",$B18="Debit Spread","Long Call/Put P/L",$B18="Stock Sale","Stock Sales",TRUE,"Other")) | T18: =IF($A18="","",IF($B18="Cash Secured Put",$K18*$M18*100,IF($B18="Covered Call",$K18*$M18*100,IF($H18="Stock",$M18*$N18,"")))) | U18: =IF(OR($A18="",$C18<>"Closed",$D18="",$E18="",$T18=0),"",$R18/$T18*365/MAX(1,$E18-$D18)) | V18: Bought to close per individual CSV. | W18: Broker CSV
A19: 15 | B19: Long Call/Put | C19: Closed | D19: 46157 | E19: 46182 | F19: =IF($E19="","",DATE(YEAR($E19),MONTH($E19),1)) | G19: SHLS | H19: Option | I19: Buy | J19: Call | K19: 10 | L19: 46311 | M19: 4 | N19: 2.4 | O19: 2.3745 | P19: 0 | Q19: =IF($A19="","",IF($H19="Stock",IF($I19="Buy",-$M19*$N19-$P19,IF($I19="Sell",IF($N19="", $M19*$O19-$P19,($O19-$N19)*$M19-$P19),"")),IF($I19="Sell",($N19-IF($O19="",0,$O19))*$M19*100-$P19,IF($I19="Buy",(IF($O19="",0,$O19)-$N19)*$M19*100-$P19,"")))) | R19: =IF($A19="","",IF($C19="Open","",$Q19)) | S19: =IF($A19="","",IFS($B19="Covered Call","Covered Call Premium",$B19="Cash Secured Put","Cash Secured Put Premium",$B19="Long Call/Put","Long Call/Put P/L",$B19="Debit Spread","Long Call/Put P/L",$B19="Stock Sale","Stock Sales",TRUE,"Other")) | T19: =IF($A19="","",IF($B19="Cash Secured Put",$K19*$M19*100,IF($B19="Covered Call",$K19*$M19*100,IF($H19="Stock",$M19*$N19,"")))) | U19: =IF(OR($A19="",$C19<>"Closed",$D19="",$E19="",$T19=0),"",$R19/$T19*365/MAX(1,$E19-$D19)) | V19: Corrected to 4 SHLS calls: buys total about $960.16; sold 2 at $2.45 and 2 at $2.30 on 2026-06-09. | W19: Broker CSV + user correction
A20: 19 | B20: Covered Call | C20: Closed | D20: 46161 | E20: 46171 | F20: =IF($E20="","",DATE(YEAR($E20),MONTH($E20),1)) | G20: PLTR | H20: Option | I20: Sell | J20: Call | K20: 150 | L20: 46191 | M20: 1 | N20: 2.24 | O20: 8.6 | P20: 0.04 | Q20: =IF($A20="","",IF($H20="Stock",IF($I20="Buy",-$M20*$N20-$P20,IF($I20="Sell",IF($N20="", $M20*$O20-$P20,($O20-$N20)*$M20-$P20),"")),IF($I20="Sell",($N20-IF($O20="",0,$O20))*$M20*100-$P20,IF($I20="Buy",(IF($O20="",0,$O20)-$N20)*$M20*100-$P20,"")))) | R20: =IF($A20="","",IF($C20="Open","",$Q20)) | S20: =IF($A20="","",IFS($B20="Covered Call","Covered Call Premium",$B20="Cash Secured Put","Cash Secured Put Premium",$B20="Long Call/Put","Long Call/Put P/L",$B20="Debit Spread","Long Call/Put P/L",$B20="Stock Sale","Stock Sales",TRUE,"Other")) | T20: =IF($A20="","",IF($B20="Cash Secured Put",$K20*$M20*100,IF($B20="Covered Call",$K20*$M20*100,IF($H20="Stock",$M20*$N20,"")))) | U20: =IF(OR($A20="",$C20<>"Closed",$D20="",$E20="",$T20=0),"",$R20/$T20*365/MAX(1,$E20-$D20)) | V20: Bought to close per joint CSV as part of PLTR roll sequence. | W20: Broker CSV
A21: 20 | B21: Cash Secured Put | C21: Closed | D21: 46161 | E21: 46171 | F21: =IF($E21="","",DATE(YEAR($E21),MONTH($E21),1)) | G21: ASTS | H21: Option | I21: Sell | J21: Put | K21: 68 | L21: 46191 | M21: 1 | N21: 4.24 | O21: 0.75 | P21: 0.04 | Q21: =IF($A21="","",IF($H21="Stock",IF($I21="Buy",-$M21*$N21-$P21,IF($I21="Sell",IF($N21="", $M21*$O21-$P21,($O21-$N21)*$M21-$P21),"")),IF($I21="Sell",($N21-IF($O21="",0,$O21))*$M21*100-$P21,IF($I21="Buy",(IF($O21="",0,$O21)-$N21)*$M21*100-$P21,"")))) | R21: =IF($A21="","",IF($C21="Open","",$Q21)) | S21: =IF($A21="","",IFS($B21="Covered Call","Covered Call Premium",$B21="Cash Secured Put","Cash Secured Put Premium",$B21="Long Call/Put","Long Call/Put P/L",$B21="Debit Spread","Long Call/Put P/L",$B21="Stock Sale","Stock Sales",TRUE,"Other")) | T21: =IF($A21="","",IF($B21="Cash Secured Put",$K21*$M21*100,IF($B21="Covered Call",$K21*$M21*100,IF($H21="Stock",$M21*$N21,"")))) | U21: =IF(OR($A21="",$C21<>"Closed",$D21="",$E21="",$T21=0),"",$R21/$T21*365/MAX(1,$E21-$D21)) | V21: Bought to close per joint CSV. | W21: Broker CSV
A22: 22 | B22: Long Call/Put | C22: Open | D22: 46160 | F22: =IF($E22="","",DATE(YEAR($E22),MONTH($E22),1)) | G22: NTNX | H22: Option | I22: Buy | J22: Call | K22: 47.5 | L22: 46311 | M22: 2 | N22: 7.15 | O22: 7.15 | P22: 0 | Q22: =IF($A22="","",IF($H22="Stock",IF($I22="Buy",-$M22*$N22-$P22,IF($I22="Sell",IF($N22="", $M22*$O22-$P22,($O22-$N22)*$M22-$P22),"")),IF($I22="Sell",($N22-IF($O22="",0,$O22))*$M22*100-$P22,IF($I22="Buy",(IF($O22="",0,$O22)-$N22)*$M22*100-$P22,"")))) | R22: =IF($A22="","",IF($C22="Open","",$Q22)) | S22: =IF($A22="","",IFS($B22="Covered Call","Covered Call Premium",$B22="Cash Secured Put","Cash Secured Put Premium",$B22="Long Call/Put","Long Call/Put P/L",$B22="Debit Spread","Long Call/Put P/L",$B22="Stock Sale","Stock Sales",TRUE,"Other")) | T22: =IF($A22="","",IF($B22="Cash Secured Put",$K22*$M22*100,IF($B22="Covered Call",$K22*$M22*100,IF($H22="Stock",$M22*$N22,"")))) | U22: =IF(OR($A22="",$C22<>"Closed",$D22="",$E22="",$T22=0),"",$R22/$T22*365/MAX(1,$E22-$D22)) | V22: Bought 1 at $7.30 and 1 at $7.00 per joint CSV; average $7.15. | W22: Broker CSV
A23: 23 | B23: Long Call/Put | C23: Closed | D23: 46161 | E23: 46168 | F23: =IF($E23="","",DATE(YEAR($E23),MONTH($E23),1)) | G23: BLDP | H23: Option | I23: Buy | J23: Call | K23: 4 | L23: 46255 | M23: 1 | N23: 1.15 | O23: 2.35 | P23: 0.08 | Q23: =IF($A23="","",IF($H23="Stock",IF($I23="Buy",-$M23*$N23-$P23,IF($I23="Sell",IF($N23="", $M23*$O23-$P23,($O23-$N23)*$M23-$P23),"")),IF($I23="Sell",($N23-IF($O23="",0,$O23))*$M23*100-$P23,IF($I23="Buy",(IF($O23="",0,$O23)-$N23)*$M23*100-$P23,"")))) | R23: =IF($A23="","",IF($C23="Open","",$Q23)) | S23: =IF($A23="","",IFS($B23="Covered Call","Covered Call Premium",$B23="Cash Secured Put","Cash Secured Put Premium",$B23="Long Call/Put","Long Call/Put P/L",$B23="Debit Spread","Long Call/Put P/L",$B23="Stock Sale","Stock Sales",TRUE,"Other")) | T23: =IF($A23="","",IF($B23="Cash Secured Put",$K23*$M23*100,IF($B23="Covered Call",$K23*$M23*100,IF($H23="Stock",$M23*$N23,"")))) | U23: =IF(OR($A23="",$C23<>"Closed",$D23="",$E23="",$T23=0),"",$R23/$T23*365/MAX(1,$E23-$D23)) | V23: Sold BLDP $4 call for $234.94 proceeds per individual CSV. | W23: Broker CSV
A24: 24 | B24: Covered Call | C24: Open | D24: 46170 | F24: =IF($E24="","",DATE(YEAR($E24),MONTH($E24),1)) | G24: PLTR | H24: Option | I24: Sell | J24: Call | K24: 160 | L24: 46191 | M24: 1 | N24: 0.98 | O24: 0.98 | P24: 0 | Q24: =IF($A24="","",IF($H24="Stock",IF($I24="Buy",-$M24*$N24-$P24,IF($I24="Sell",IF($N24="", $M24*$O24-$P24,($O24-$N24)*$M24-$P24),"")),IF($I24="Sell",($N24-IF($O24="",0,$O24))*$M24*100-$P24,IF($I24="Buy",(IF($O24="",0,$O24)-$N24)*$M24*100-$P24,"")))) | R24: =IF($A24="","",IF($C24="Open","",$Q24)) | S24: =IF($A24="","",IFS($B24="Covered Call","Covered Call Premium",$B24="Cash Secured Put","Cash Secured Put Premium",$B24="Long Call/Put","Long Call/Put P/L",$B24="Debit Spread","Long Call/Put P/L",$B24="Stock Sale","Stock Sales",TRUE,"Other")) | T24: =IF($A24="","",IF($B24="Cash Secured Put",$K24*$M24*100,IF($B24="Covered Call",$K24*$M24*100,IF($H24="Stock",$M24*$N24,"")))) | U24: =IF(OR($A24="",$C24<>"Closed",$D24="",$E24="",$T24=0),"",$R24/$T24*365/MAX(1,$E24-$D24)) | V24: Open PLTR $160 covered call per joint CSV. | W24: Broker CSV
A25: 25 | B25: Cash Secured Put | C25: Open | D25: 46170 | F25: =IF($E25="","",DATE(YEAR($E25),MONTH($E25),1)) | G25: SOFI | H25: Option | I25: Sell | J25: Put | K25: 18 | L25: 46191 | M25: 1 | N25: 1.49 | O25: 1.49 | P25: 0 | Q25: =IF($A25="","",IF($H25="Stock",IF($I25="Buy",-$M25*$N25-$P25,IF($I25="Sell",IF($N25="", $M25*$O25-$P25,($O25-$N25)*$M25-$P25),"")),IF($I25="Sell",($N25-IF($O25="",0,$O25))*$M25*100-$P25,IF($I25="Buy",(IF($O25="",0,$O25)-$N25)*$M25*100-$P25,"")))) | R25: =IF($A25="","",IF($C25="Open","",$Q25)) | S25: =IF($A25="","",IFS($B25="Covered Call","Covered Call Premium",$B25="Cash Secured Put","Cash Secured Put Premium",$B25="Long Call/Put","Long Call/Put P/L",$B25="Debit Spread","Long Call/Put P/L",$B25="Stock Sale","Stock Sales",TRUE,"Other")) | T25: =IF($A25="","",IF($B25="Cash Secured Put",$K25*$M25*100,IF($B25="Covered Call",$K25*$M25*100,IF($H25="Stock",$M25*$N25,"")))) | U25: =IF(OR($A25="",$C25<>"Closed",$D25="",$E25="",$T25=0),"",$R25/$T25*365/MAX(1,$E25-$D25)) | V25: Open SOFI $18 put per joint CSV; corrected credit to $1.49. | W25: Broker CSV
A26: 26 | B26: Covered Call | C26: Open | D26: 46170 | F26: =IF($E26="","",DATE(YEAR($E26),MONTH($E26),1)) | G26: AEHR | H26: Option | I26: Sell | J26: Call | K26: 160 | L26: 46205 | M26: 1 | N26: 4.05 | O26: 4.05 | P26: 0 | Q26: =IF($A26="","",IF($H26="Stock",IF($I26="Buy",-$M26*$N26-$P26,IF($I26="Sell",IF($N26="", $M26*$O26-$P26,($O26-$N26)*$M26-$P26),"")),IF($I26="Sell",($N26-IF($O26="",0,$O26))*$M26*100-$P26,IF($I26="Buy",(IF($O26="",0,$O26)-$N26)*$M26*100-$P26,"")))) | R26: =IF($A26="","",IF($C26="Open","",$Q26)) | S26: =IF($A26="","",IFS($B26="Covered Call","Covered Call Premium",$B26="Cash Secured Put","Cash Secured Put Premium",$B26="Long Call/Put","Long Call/Put P/L",$B26="Debit Spread","Long Call/Put P/L",$B26="Stock Sale","Stock Sales",TRUE,"Other")) | T26: =IF($A26="","",IF($B26="Cash Secured Put",$K26*$M26*100,IF($B26="Covered Call",$K26*$M26*100,IF($H26="Stock",$M26*$N26,"")))) | U26: =IF(OR($A26="",$C26<>"Closed",$D26="",$E26="",$T26=0),"",$R26/$T26*365/MAX(1,$E26-$D26)) | V26: Open AEHR $160 7/2 covered call per individual CSV. | W26: Broker CSV
A27: 27 | B27: Covered Call | C27: Closed | D27: 46169 | E27: 46182 | F27: =IF($E27="","",DATE(YEAR($E27),MONTH($E27),1)) | G27: NTNX | H27: Option | I27: Sell | J27: Call | K27: 55 | L27: 46191 | M27: 1 | N27: 0.95 | O27: 0.7 | P27: 0.08 | Q27: =IF($A27="","",IF($H27="Stock",IF($I27="Buy",-$M27*$N27-$P27,IF($I27="Sell",IF($N27="", $M27*$O27-$P27,($O27-$N27)*$M27-$P27),"")),IF($I27="Sell",($N27-IF($O27="",0,$O27))*$M27*100-$P27,IF($I27="Buy",(IF($O27="",0,$O27)-$N27)*$M27*100-$P27,"")))) | R27: =IF($A27="","",IF($C27="Open","",$Q27)) | S27: =IF($A27="","",IFS($B27="Covered Call","Covered Call Premium",$B27="Cash Secured Put","Cash Secured Put Premium",$B27="Long Call/Put","Long Call/Put P/L",$B27="Debit Spread","Long Call/Put P/L",$B27="Stock Sale","Stock Sales",TRUE,"Other")) | T27: =IF($A27="","",IF($B27="Cash Secured Put",$K27*$M27*100,IF($B27="Covered Call",$K27*$M27*100,IF($H27="Stock",$M27*$N27,"")))) | U27: =IF(OR($A27="",$C27<>"Closed",$D27="",$E27="",$T27=0),"",$R27/$T27*365/MAX(1,$E27-$D27)) | V27: Bought to close NTNX $55 covered call per joint CSV. | W27: Broker CSV
A28: 28 | B28: Long Call/Put | C28: Closed | D28: 46168 | E28: 46178 | F28: =IF($E28="","",DATE(YEAR($E28),MONTH($E28),1)) | G28: SOFI | H28: Option | I28: Buy | J28: Call | K28: 22 | L28: 46738 | M28: 2 | N28: 4 | O28: 4.05 | P28: 0.19 | Q28: =IF($A28="","",IF($H28="Stock",IF($I28="Buy",-$M28*$N28-$P28,IF($I28="Sell",IF($N28="", $M28*$O28-$P28,($O28-$N28)*$M28-$P28),"")),IF($I28="Sell",($N28-IF($O28="",0,$O28))*$M28*100-$P28,IF($I28="Buy",(IF($O28="",0,$O28)-$N28)*$M28*100-$P28,"")))) | R28: =IF($A28="","",IF($C28="Open","",$Q28)) | S28: =IF($A28="","",IFS($B28="Covered Call","Covered Call Premium",$B28="Cash Secured Put","Cash Secured Put Premium",$B28="Long Call/Put","Long Call/Put P/L",$B28="Debit Spread","Long Call/Put P/L",$B28="Stock Sale","Stock Sales",TRUE,"Other")) | T28: =IF($A28="","",IF($B28="Cash Secured Put",$K28*$M28*100,IF($B28="Covered Call",$K28*$M28*100,IF($H28="Stock",$M28*$N28,"")))) | U28: =IF(OR($A28="",$C28<>"Closed",$D28="",$E28="",$T28=0),"",$R28/$T28*365/MAX(1,$E28-$D28)) | V28: Sold to close 2 SOFI $22 calls at $4.05 per joint CSV. | W28: Broker CSV
A29: 29 | B29: Long Call/Put | C29: Open | D29: 46170 | F29: =IF($E29="","",DATE(YEAR($E29),MONTH($E29),1)) | G29: FIVN | H29: Option | I29: Buy | J29: Call | K29: 25 | L29: 46311 | M29: 2 | N29: 4.3 | O29: 4.3 | P29: 0 | Q29: =IF($A29="","",IF($H29="Stock",IF($I29="Buy",-$M29*$N29-$P29,IF($I29="Sell",IF($N29="", $M29*$O29-$P29,($O29-$N29)*$M29-$P29),"")),IF($I29="Sell",($N29-IF($O29="",0,$O29))*$M29*100-$P29,IF($I29="Buy",(IF($O29="",0,$O29)-$N29)*$M29*100-$P29,"")))) | R29: =IF($A29="","",IF($C29="Open","",$Q29)) | S29: =IF($A29="","",IFS($B29="Covered Call","Covered Call Premium",$B29="Cash Secured Put","Cash Secured Put Premium",$B29="Long Call/Put","Long Call/Put P/L",$B29="Debit Spread","Long Call/Put P/L",$B29="Stock Sale","Stock Sales",TRUE,"Other")) | T29: =IF($A29="","",IF($B29="Cash Secured Put",$K29*$M29*100,IF($B29="Covered Call",$K29*$M29*100,IF($H29="Stock",$M29*$N29,"")))) | U29: =IF(OR($A29="",$C29<>"Closed",$D29="",$E29="",$T29=0),"",$R29/$T29*365/MAX(1,$E29-$D29)) | V29: Open FIVN $25 calls per joint CSV. | W29: Broker CSV
A30: 30 | B30: Long Call/Put | C30: Closed | D30: 46164 | E30: 46177 | F30: =IF($E30="","",DATE(YEAR($E30),MONTH($E30),1)) | G30: SONY | H30: Option | I30: Buy | J30: Call | K30: 30 | L30: 46283 | M30: 6 | N30: 0.36 | O30: 0.3 | P30: 0.27 | Q30: =IF($A30="","",IF($H30="Stock",IF($I30="Buy",-$M30*$N30-$P30,IF($I30="Sell",IF($N30="", $M30*$O30-$P30,($O30-$N30)*$M30-$P30),"")),IF($I30="Sell",($N30-IF($O30="",0,$O30))*$M30*100-$P30,IF($I30="Buy",(IF($O30="",0,$O30)-$N30)*$M30*100-$P30,"")))) | R30: =IF($A30="","",IF($C30="Open","",$Q30)) | S30: =IF($A30="","",IFS($B30="Covered Call","Covered Call Premium",$B30="Cash Secured Put","Cash Secured Put Premium",$B30="Long Call/Put","Long Call/Put P/L",$B30="Debit Spread","Long Call/Put P/L",$B30="Stock Sale","Stock Sales",TRUE,"Other")) | T30: =IF($A30="","",IF($B30="Cash Secured Put",$K30*$M30*100,IF($B30="Covered Call",$K30*$M30*100,IF($H30="Stock",$M30*$N30,"")))) | U30: =IF(OR($A30="",$C30<>"Closed",$D30="",$E30="",$T30=0),"",$R30/$T30*365/MAX(1,$E30-$D30)) | V30: Sold to close 6 SONY $30 calls at $0.30 per individual CSV. | W30: Broker CSV
A31: 31 | B31: Long Call/Put | C31: Closed | D31: 46168 | E31: 46184 | F31: =IF($E31="","",DATE(YEAR($E31),MONTH($E31),1)) | G31: SONY | H31: Option | I31: Buy | J31: Call | K31: 22.5 | L31: 46374 | M31: 5 | N31: 2.8 | O31: 1.85 | P31: 0 | Q31: =IF($A31="","",IF($H31="Stock",IF($I31="Buy",-$M31*$N31-$P31,IF($I31="Sell",IF($N31="", $M31*$O31-$P31,($O31-$N31)*$M31-$P31),"")),IF($I31="Sell",($N31-IF($O31="",0,$O31))*$M31*100-$P31,IF($I31="Buy",(IF($O31="",0,$O31)-$N31)*$M31*100-$P31,"")))) | R31: =IF($A31="","",IF($C31="Open","",$Q31)) | S31: =IF($A31="","",IFS($B31="Covered Call","Covered Call Premium",$B31="Cash Secured Put","Cash Secured Put Premium",$B31="Long Call/Put","Long Call/Put P/L",$B31="Debit Spread","Long Call/Put P/L",$B31="Stock Sale","Stock Sales",TRUE,"Other")) | T31: =IF($A31="","",IF($B31="Cash Secured Put",$K31*$M31*100,IF($B31="Covered Call",$K31*$M31*100,IF($H31="Stock",$M31*$N31,"")))) | U31: =IF(OR($A31="",$C31<>"Closed",$D31="",$E31="",$T31=0),"",$R31/$T31*365/MAX(1,$E31-$D31)) | V31: Closed all 5 SONY $22.50 12/18/26 calls at $1.85 each on 2026-06-11. User noted lesson: copy trading someone else did not work out. | W31: User trade update
A32: 32 | B32: Long Call/Put | C32: Closed | D32: 46168 | E32: 46184 | F32: =IF($E32="","",DATE(YEAR($E32),MONTH($E32),1)) | G32: SONY | H32: Option | I32: Buy | J32: Call | K32: 22.5 | L32: 46402 | M32: 7 | N32: 2.77 | O32: 2 | P32: 0 | Q32: =IF($A32="","",IF($H32="Stock",IF($I32="Buy",-$M32*$N32-$P32,IF($I32="Sell",IF($N32="", $M32*$O32-$P32,($O32-$N32)*$M32-$P32),"")),IF($I32="Sell",($N32-IF($O32="",0,$O32))*$M32*100-$P32,IF($I32="Buy",(IF($O32="",0,$O32)-$N32)*$M32*100-$P32,"")))) | R32: =IF($A32="","",IF($C32="Open","",$Q32)) | S32: =IF($A32="","",IFS($B32="Covered Call","Covered Call Premium",$B32="Cash Secured Put","Cash Secured Put Premium",$B32="Long Call/Put","Long Call/Put P/L",$B32="Debit Spread","Long Call/Put P/L",$B32="Stock Sale","Stock Sales",TRUE,"Other")) | T32: =IF($A32="","",IF($B32="Cash Secured Put",$K32*$M32*100,IF($B32="Covered Call",$K32*$M32*100,IF($H32="Stock",$M32*$N32,"")))) | U32: =IF(OR($A32="",$C32<>"Closed",$D32="",$E32="",$T32=0),"",$R32/$T32*365/MAX(1,$E32-$D32)) | V32: Closed all 7 SONY $22.50 1/15/27 calls at $2.00 each on 2026-06-11. User noted lesson: copy trading someone else did not work out. | W32: User trade update
A33: 35 | B33: Covered Call | C33: Open | D33: 46171 | F33: =IF($E33="","",DATE(YEAR($E33),MONTH($E33),1)) | G33: PLTR | H33: Option | I33: Sell | J33: Call | K33: 220 | L33: 46402 | M33: 1 | N33: 12.5 | O33: 12.5 | P33: 0 | Q33: =IF($A33="","",IF($H33="Stock",IF($I33="Buy",-$M33*$N33-$P33,IF($I33="Sell",IF($N33="", $M33*$O33-$P33,($O33-$N33)*$M33-$P33),"")),IF($I33="Sell",($N33-IF($O33="",0,$O33))*$M33*100-$P33,IF($I33="Buy",(IF($O33="",0,$O33)-$N33)*$M33*100-$P33,"")))) | R33: =IF($A33="","",IF($C33="Open","",$Q33)) | S33: =IF($A33="","",IFS($B33="Covered Call","Covered Call Premium",$B33="Cash Secured Put","Cash Secured Put Premium",$B33="Long Call/Put","Long Call/Put P/L",$B33="Debit Spread","Long Call/Put P/L",$B33="Stock Sale","Stock Sales",TRUE,"Other")) | T33: =IF($A33="","",IF($B33="Cash Secured Put",$K33*$M33*100,IF($B33="Covered Call",$K33*$M33*100,IF($H33="Stock",$M33*$N33,"")))) | U33: =IF(OR($A33="",$C33<>"Closed",$D33="",$E33="",$T33=0),"",$R33/$T33*365/MAX(1,$E33-$D33)) | V33: Final open PLTR $220 covered call from 2026-05-29 roll sequence per joint CSV. | W33: Broker CSV
A34: 36 | B34: Cash Secured Put | C34: Open | D34: 46174 | F34: =IF($E34="","",DATE(YEAR($E34),MONTH($E34),1)) | G34: CRNC | H34: Option | I34: Sell | J34: Put | K34: 12 | L34: 46191 | M34: 2 | N34: 1.05 | O34: 1.05 | P34: 0 | Q34: =IF($A34="","",IF($H34="Stock",IF($I34="Buy",-$M34*$N34-$P34,IF($I34="Sell",IF($N34="", $M34*$O34-$P34,($O34-$N34)*$M34-$P34),"")),IF($I34="Sell",($N34-IF($O34="",0,$O34))*$M34*100-$P34,IF($I34="Buy",(IF($O34="",0,$O34)-$N34)*$M34*100-$P34,"")))) | R34: =IF($A34="","",IF($C34="Open","",$Q34)) | S34: =IF($A34="","",IFS($B34="Covered Call","Covered Call Premium",$B34="Cash Secured Put","Cash Secured Put Premium",$B34="Long Call/Put","Long Call/Put P/L",$B34="Debit Spread","Long Call/Put P/L",$B34="Stock Sale","Stock Sales",TRUE,"Other")) | T34: =IF($A34="","",IF($B34="Cash Secured Put",$K34*$M34*100,IF($B34="Covered Call",$K34*$M34*100,IF($H34="Stock",$M34*$N34,"")))) | U34: =IF(OR($A34="",$C34<>"Closed",$D34="",$E34="",$T34=0),"",$R34/$T34*365/MAX(1,$E34-$D34)) | V34: Open 2 CRNC $12 cash secured puts per joint CSV. | W34: Broker CSV
A35: 37 | B35: Long Call/Put | C35: Open | D35: 46174 | F35: =IF($E35="","",DATE(YEAR($E35),MONTH($E35),1)) | G35: CRNC | H35: Option | I35: Buy | J35: Call | K35: 10 | L35: 46255 | M35: 6 | N35: 3.83 | O35: 3.83 | P35: 0 | Q35: =IF($A35="","",IF($H35="Stock",IF($I35="Buy",-$M35*$N35-$P35,IF($I35="Sell",IF($N35="", $M35*$O35-$P35,($O35-$N35)*$M35-$P35),"")),IF($I35="Sell",($N35-IF($O35="",0,$O35))*$M35*100-$P35,IF($I35="Buy",(IF($O35="",0,$O35)-$N35)*$M35*100-$P35,"")))) | R35: =IF($A35="","",IF($C35="Open","",$Q35)) | S35: =IF($A35="","",IFS($B35="Covered Call","Covered Call Premium",$B35="Cash Secured Put","Cash Secured Put Premium",$B35="Long Call/Put","Long Call/Put P/L",$B35="Debit Spread","Long Call/Put P/L",$B35="Stock Sale","Stock Sales",TRUE,"Other")) | T35: =IF($A35="","",IF($B35="Cash Secured Put",$K35*$M35*100,IF($B35="Covered Call",$K35*$M35*100,IF($H35="Stock",$M35*$N35,"")))) | U35: =IF(OR($A35="",$C35<>"Closed",$D35="",$E35="",$T35=0),"",$R35/$T35*365/MAX(1,$E35-$D35)) | V35: Open CRNC $10 calls: 2 at $4.10, 2 at $3.60, 2 at $3.80; weighted average about $3.83. | W35: Broker CSV
A36: 38 | B36: Covered Call | C36: Closed | D36: 46171 | E36: 46171 | F36: =IF($E36="","",DATE(YEAR($E36),MONTH($E36),1)) | G36: PLTR | H36: Option | I36: Sell | J36: Call | K36: 152.5 | L36: 46191 | M36: 1 | N36: 10.02 | O36: 10.75 | P36: 0.08 | Q36: =IF($A36="","",IF($H36="Stock",IF($I36="Buy",-$M36*$N36-$P36,IF($I36="Sell",IF($N36="", $M36*$O36-$P36,($O36-$N36)*$M36-$P36),"")),IF($I36="Sell",($N36-IF($O36="",0,$O36))*$M36*100-$P36,IF($I36="Buy",(IF($O36="",0,$O36)-$N36)*$M36*100-$P36,"")))) | R36: =IF($A36="","",IF($C36="Open","",$Q36)) | S36: =IF($A36="","",IFS($B36="Covered Call","Covered Call Premium",$B36="Cash Secured Put","Cash Secured Put Premium",$B36="Long Call/Put","Long Call/Put P/L",$B36="Debit Spread","Long Call/Put P/L",$B36="Stock Sale","Stock Sales",TRUE,"Other")) | T36: =IF($A36="","",IF($B36="Cash Secured Put",$K36*$M36*100,IF($B36="Covered Call",$K36*$M36*100,IF($H36="Stock",$M36*$N36,"")))) | U36: =IF(OR($A36="",$C36<>"Closed",$D36="",$E36="",$T36=0),"",$R36/$T36*365/MAX(1,$E36-$D36)) | V36: Intraday PLTR roll leg from joint CSV. | W36: Broker CSV
A37: 39 | B37: Covered Call | C37: Closed | D37: 46171 | E37: 46171 | F37: =IF($E37="","",DATE(YEAR($E37),MONTH($E37),1)) | G37: PLTR | H37: Option | I37: Sell | J37: Call | K37: 220 | L37: 46402 | M37: 1 | N37: 10.6 | O37: 12.02 | P37: 0.08 | Q37: =IF($A37="","",IF($H37="Stock",IF($I37="Buy",-$M37*$N37-$P37,IF($I37="Sell",IF($N37="", $M37*$O37-$P37,($O37-$N37)*$M37-$P37),"")),IF($I37="Sell",($N37-IF($O37="",0,$O37))*$M37*100-$P37,IF($I37="Buy",(IF($O37="",0,$O37)-$N37)*$M37*100-$P37,"")))) | R37: =IF($A37="","",IF($C37="Open","",$Q37)) | S37: =IF($A37="","",IFS($B37="Covered Call","Covered Call Premium",$B37="Cash Secured Put","Cash Secured Put Premium",$B37="Long Call/Put","Long Call/Put P/L",$B37="Debit Spread","Long Call/Put P/L",$B37="Stock Sale","Stock Sales",TRUE,"Other")) | T37: =IF($A37="","",IF($B37="Cash Secured Put",$K37*$M37*100,IF($B37="Covered Call",$K37*$M37*100,IF($H37="Stock",$M37*$N37,"")))) | U37: =IF(OR($A37="",$C37<>"Closed",$D37="",$E37="",$T37=0),"",$R37/$T37*365/MAX(1,$E37-$D37)) | V37: Intermediate PLTR $220 roll leg from joint CSV. | W37: Broker CSV
A38: 40 | B38: Covered Call | C38: Closed | D38: 46169 | E38: 46169 | F38: =IF($E38="","",DATE(YEAR($E38),MONTH($E38),1)) | G38: HOOD | H38: Option | I38: Sell | J38: Call | K38: 90 | L38: 46191 | M38: 1 | N38: 0.98 | O38: 0.95 | P38: 0.08 | Q38: =IF($A38="","",IF($H38="Stock",IF($I38="Buy",-$M38*$N38-$P38,IF($I38="Sell",IF($N38="", $M38*$O38-$P38,($O38-$N38)*$M38-$P38),"")),IF($I38="Sell",($N38-IF($O38="",0,$O38))*$M38*100-$P38,IF($I38="Buy",(IF($O38="",0,$O38)-$N38)*$M38*100-$P38,"")))) | R38: =IF($A38="","",IF($C38="Open","",$Q38)) | S38: =IF($A38="","",IFS($B38="Covered Call","Covered Call Premium",$B38="Cash Secured Put","Cash Secured Put Premium",$B38="Long Call/Put","Long Call/Put P/L",$B38="Debit Spread","Long Call/Put P/L",$B38="Stock Sale","Stock Sales",TRUE,"Other")) | T38: =IF($A38="","",IF($B38="Cash Secured Put",$K38*$M38*100,IF($B38="Covered Call",$K38*$M38*100,IF($H38="Stock",$M38*$N38,"")))) | U38: =IF(OR($A38="",$C38<>"Closed",$D38="",$E38="",$T38=0),"",$R38/$T38*365/MAX(1,$E38-$D38)) | V38: Opened and closed HOOD $90 call per joint CSV. | W38: Broker CSV
A39: 41 | B39: Covered Call | C39: Closed | D39: 46171 | E39: 46174 | F39: =IF($E39="","",DATE(YEAR($E39),MONTH($E39),1)) | G39: HOOD | H39: Option | I39: Sell | J39: Call | K39: 120 | L39: 46191 | M39: 1 | N39: 0.73 | O39: 0.63 | P39: 0.08 | Q39: =IF($A39="","",IF($H39="Stock",IF($I39="Buy",-$M39*$N39-$P39,IF($I39="Sell",IF($N39="", $M39*$O39-$P39,($O39-$N39)*$M39-$P39),"")),IF($I39="Sell",($N39-IF($O39="",0,$O39))*$M39*100-$P39,IF($I39="Buy",(IF($O39="",0,$O39)-$N39)*$M39*100-$P39,"")))) | R39: =IF($A39="","",IF($C39="Open","",$Q39)) | S39: =IF($A39="","",IFS($B39="Covered Call","Covered Call Premium",$B39="Cash Secured Put","Cash Secured Put Premium",$B39="Long Call/Put","Long Call/Put P/L",$B39="Debit Spread","Long Call/Put P/L",$B39="Stock Sale","Stock Sales",TRUE,"Other")) | T39: =IF($A39="","",IF($B39="Cash Secured Put",$K39*$M39*100,IF($B39="Covered Call",$K39*$M39*100,IF($H39="Stock",$M39*$N39,"")))) | U39: =IF(OR($A39="",$C39<>"Closed",$D39="",$E39="",$T39=0),"",$R39/$T39*365/MAX(1,$E39-$D39)) | V39: Opened and closed HOOD $120 call per joint CSV. | W39: Broker CSV
A40: 42 | B40: Covered Call | C40: Closed | D40: 46128 | E40: 46182 | F40: =IF($E40="","",DATE(YEAR($E40),MONTH($E40),1)) | G40: AEHR | H40: Option | I40: Sell | J40: Call | K40: 110 | L40: 46283 | M40: 1 | N40: 18.52 | O40: 20.25 | P40: 0.08 | Q40: =IF($A40="","",IF($H40="Stock",IF($I40="Buy",-$M40*$N40-$P40,IF($I40="Sell",IF($N40="", $M40*$O40-$P40,($O40-$N40)*$M40-$P40),"")),IF($I40="Sell",($N40-IF($O40="",0,$O40))*$M40*100-$P40,IF($I40="Buy",(IF($O40="",0,$O40)-$N40)*$M40*100-$P40,"")))) | R40: =IF($A40="","",IF($C40="Open","",$Q40)) | S40: =IF($A40="","",IFS($B40="Covered Call","Covered Call Premium",$B40="Cash Secured Put","Cash Secured Put Premium",$B40="Long Call/Put","Long Call/Put P/L",$B40="Debit Spread","Long Call/Put P/L",$B40="Stock Sale","Stock Sales",TRUE,"Other")) | T40: =IF($A40="","",IF($B40="Cash Secured Put",$K40*$M40*100,IF($B40="Covered Call",$K40*$M40*100,IF($H40="Stock",$M40*$N40,"")))) | U40: =IF(OR($A40="",$C40<>"Closed",$D40="",$E40="",$T40=0),"",$R40/$T40*365/MAX(1,$E40-$D40)) | V40: Rolled to AEHR $160 1/15/27; closed per individual CSV. | W40: Broker CSV
A41: 43 | B41: Covered Call | C41: Open | D41: 46182 | F41: =IF($E41="","",DATE(YEAR($E41),MONTH($E41),1)) | G41: AEHR | H41: Option | I41: Sell | J41: Call | K41: 160 | L41: 46402 | M41: 1 | N41: 22.05 | O41: 22.05 | P41: 0 | Q41: =IF($A41="","",IF($H41="Stock",IF($I41="Buy",-$M41*$N41-$P41,IF($I41="Sell",IF($N41="", $M41*$O41-$P41,($O41-$N41)*$M41-$P41),"")),IF($I41="Sell",($N41-IF($O41="",0,$O41))*$M41*100-$P41,IF($I41="Buy",(IF($O41="",0,$O41)-$N41)*$M41*100-$P41,"")))) | R41: =IF($A41="","",IF($C41="Open","",$Q41)) | S41: =IF($A41="","",IFS($B41="Covered Call","Covered Call Premium",$B41="Cash Secured Put","Cash Secured Put Premium",$B41="Long Call/Put","Long Call/Put P/L",$B41="Debit Spread","Long Call/Put P/L",$B41="Stock Sale","Stock Sales",TRUE,"Other")) | T41: =IF($A41="","",IF($B41="Cash Secured Put",$K41*$M41*100,IF($B41="Covered Call",$K41*$M41*100,IF($H41="Stock",$M41*$N41,"")))) | U41: =IF(OR($A41="",$C41<>"Closed",$D41="",$E41="",$T41=0),"",$R41/$T41*365/MAX(1,$E41-$D41)) | V41: Open AEHR $160 1/15/27 covered call from roll per individual CSV. | W41: Broker CSV
A42: 44 | B42: Cash Secured Put | C42: Open | D42: 46164 | F42: =IF($E42="","",DATE(YEAR($E42),MONTH($E42),1)) | G42: NEXT | H42: Option | I42: Sell | J42: Put | K42: 8 | L42: 46191 | M42: 1 | N42: 0.45 | O42: 0.45 | P42: 0 | Q42: =IF($A42="","",IF($H42="Stock",IF($I42="Buy",-$M42*$N42-$P42,IF($I42="Sell",IF($N42="", $M42*$O42-$P42,($O42-$N42)*$M42-$P42),"")),IF($I42="Sell",($N42-IF($O42="",0,$O42))*$M42*100-$P42,IF($I42="Buy",(IF($O42="",0,$O42)-$N42)*$M42*100-$P42,"")))) | R42: =IF($A42="","",IF($C42="Open","",$Q42)) | S42: =IF($A42="","",IFS($B42="Covered Call","Covered Call Premium",$B42="Cash Secured Put","Cash Secured Put Premium",$B42="Long Call/Put","Long Call/Put P/L",$B42="Debit Spread","Long Call/Put P/L",$B42="Stock Sale","Stock Sales",TRUE,"Other")) | T42: =IF($A42="","",IF($B42="Cash Secured Put",$K42*$M42*100,IF($B42="Covered Call",$K42*$M42*100,IF($H42="Stock",$M42*$N42,"")))) | U42: =IF(OR($A42="",$C42<>"Closed",$D42="",$E42="",$T42=0),"",$R42/$T42*365/MAX(1,$E42-$D42)) | V42: Open NEXT $8 put per joint CSV. | W42: Broker CSV
A43: 45 | B43: Cash Secured Put | C43: Open | D43: 46182 | F43: =IF($E43="","",DATE(YEAR($E43),MONTH($E43),1)) | G43: ADEA | H43: Option | I43: Sell | J43: Put | K43: 30 | L43: 46220 | M43: 1 | N43: 3.6 | O43: 3.6 | P43: 0 | Q43: =IF($A43="","",IF($H43="Stock",IF($I43="Buy",-$M43*$N43-$P43,IF($I43="Sell",IF($N43="", $M43*$O43-$P43,($O43-$N43)*$M43-$P43),"")),IF($I43="Sell",($N43-IF($O43="",0,$O43))*$M43*100-$P43,IF($I43="Buy",(IF($O43="",0,$O43)-$N43)*$M43*100-$P43,"")))) | R43: =IF($A43="","",IF($C43="Open","",$Q43)) | S43: =IF($A43="","",IFS($B43="Covered Call","Covered Call Premium",$B43="Cash Secured Put","Cash Secured Put Premium",$B43="Long Call/Put","Long Call/Put P/L",$B43="Debit Spread","Long Call/Put P/L",$B43="Stock Sale","Stock Sales",TRUE,"Other")) | T43: =IF($A43="","",IF($B43="Cash Secured Put",$K43*$M43*100,IF($B43="Covered Call",$K43*$M43*100,IF($H43="Stock",$M43*$N43,"")))) | U43: =IF(OR($A43="",$C43<>"Closed",$D43="",$E43="",$T43=0),"",$R43/$T43*365/MAX(1,$E43-$D43)) | V43: Open ADEA $30 cash secured put per joint CSV. | W43: Broker CSV
A44: 46 | B44: Long Call/Put | C44: Open | D44: 46178 | F44: =IF($E44="","",DATE(YEAR($E44),MONTH($E44),1)) | G44: ADEA | H44: Option | I44: Buy | J44: Call | K44: 30 | L44: 46283 | M44: 2 | N44: 6.6 | O44: 6.6 | P44: 0 | Q44: =IF($A44="","",IF($H44="Stock",IF($I44="Buy",-$M44*$N44-$P44,IF($I44="Sell",IF($N44="", $M44*$O44-$P44,($O44-$N44)*$M44-$P44),"")),IF($I44="Sell",($N44-IF($O44="",0,$O44))*$M44*100-$P44,IF($I44="Buy",(IF($O44="",0,$O44)-$N44)*$M44*100-$P44,"")))) | R44: =IF($A44="","",IF($C44="Open","",$Q44)) | S44: =IF($A44="","",IFS($B44="Covered Call","Covered Call Premium",$B44="Cash Secured Put","Cash Secured Put Premium",$B44="Long Call/Put","Long Call/Put P/L",$B44="Debit Spread","Long Call/Put P/L",$B44="Stock Sale","Stock Sales",TRUE,"Other")) | T44: =IF($A44="","",IF($B44="Cash Secured Put",$K44*$M44*100,IF($B44="Covered Call",$K44*$M44*100,IF($H44="Stock",$M44*$N44,"")))) | U44: =IF(OR($A44="",$C44<>"Closed",$D44="",$E44="",$T44=0),"",$R44/$T44*365/MAX(1,$E44-$D44)) | V44: Open ADEA $30 calls per individual CSV. | W44: Broker CSV
A45: 47 | B45: Long Call/Put | C45: Open | D45: 46178 | F45: =IF($E45="","",DATE(YEAR($E45),MONTH($E45),1)) | G45: GRAB | H45: Option | I45: Buy | J45: Call | K45: 5 | L45: 46738 | M45: 40 | N45: 0.59 | O45: 0.59 | P45: 0 | Q45: =IF($A45="","",IF($H45="Stock",IF($I45="Buy",-$M45*$N45-$P45,IF($I45="Sell",IF($N45="", $M45*$O45-$P45,($O45-$N45)*$M45-$P45),"")),IF($I45="Sell",($N45-IF($O45="",0,$O45))*$M45*100-$P45,IF($I45="Buy",(IF($O45="",0,$O45)-$N45)*$M45*100-$P45,"")))) | R45: =IF($A45="","",IF($C45="Open","",$Q45)) | S45: =IF($A45="","",IFS($B45="Covered Call","Covered Call Premium",$B45="Cash Secured Put","Cash Secured Put Premium",$B45="Long Call/Put","Long Call/Put P/L",$B45="Debit Spread","Long Call/Put P/L",$B45="Stock Sale","Stock Sales",TRUE,"Other")) | T45: =IF($A45="","",IF($B45="Cash Secured Put",$K45*$M45*100,IF($B45="Covered Call",$K45*$M45*100,IF($H45="Stock",$M45*$N45,"")))) | U45: =IF(OR($A45="",$C45<>"Closed",$D45="",$E45="",$T45=0),"",$R45/$T45*365/MAX(1,$E45-$D45)) | V45: Open GRAB $5 calls per individual CSV. | W45: Broker CSV
A46: 48 | B46: Long Call/Put | C46: Open | D46: 46176 | F46: =IF($E46="","",DATE(YEAR($E46),MONTH($E46),1)) | G46: CRNC | H46: Option | I46: Buy | J46: Call | K46: 15 | L46: 46402 | M46: 2 | N46: 3.3 | O46: 3.3 | P46: 0 | Q46: =IF($A46="","",IF($H46="Stock",IF($I46="Buy",-$M46*$N46-$P46,IF($I46="Sell",IF($N46="", $M46*$O46-$P46,($O46-$N46)*$M46-$P46),"")),IF($I46="Sell",($N46-IF($O46="",0,$O46))*$M46*100-$P46,IF($I46="Buy",(IF($O46="",0,$O46)-$N46)*$M46*100-$P46,"")))) | R46: =IF($A46="","",IF($C46="Open","",$Q46)) | S46: =IF($A46="","",IFS($B46="Covered Call","Covered Call Premium",$B46="Cash Secured Put","Cash Secured Put Premium",$B46="Long Call/Put","Long Call/Put P/L",$B46="Debit Spread","Long Call/Put P/L",$B46="Stock Sale","Stock Sales",TRUE,"Other")) | T46: =IF($A46="","",IF($B46="Cash Secured Put",$K46*$M46*100,IF($B46="Covered Call",$K46*$M46*100,IF($H46="Stock",$M46*$N46,"")))) | U46: =IF(OR($A46="",$C46<>"Closed",$D46="",$E46="",$T46=0),"",$R46/$T46*365/MAX(1,$E46-$D46)) | V46: Open CRNC $15 calls per joint CSV. | W46: Broker CSV
A47: 49 | B47: Long Call/Put | C47: Open | D47: 46176 | F47: =IF($E47="","",DATE(YEAR($E47),MONTH($E47),1)) | G47: FIVN | H47: Option | I47: Buy | J47: Call | K47: 25 | L47: 46255 | M47: 2 | N47: 4 | O47: 4 | P47: 0 | Q47: =IF($A47="","",IF($H47="Stock",IF($I47="Buy",-$M47*$N47-$P47,IF($I47="Sell",IF($N47="", $M47*$O47-$P47,($O47-$N47)*$M47-$P47),"")),IF($I47="Sell",($N47-IF($O47="",0,$O47))*$M47*100-$P47,IF($I47="Buy",(IF($O47="",0,$O47)-$N47)*$M47*100-$P47,"")))) | R47: =IF($A47="","",IF($C47="Open","",$Q47)) | S47: =IF($A47="","",IFS($B47="Covered Call","Covered Call Premium",$B47="Cash Secured Put","Cash Secured Put Premium",$B47="Long Call/Put","Long Call/Put P/L",$B47="Debit Spread","Long Call/Put P/L",$B47="Stock Sale","Stock Sales",TRUE,"Other")) | T47: =IF($A47="","",IF($B47="Cash Secured Put",$K47*$M47*100,IF($B47="Covered Call",$K47*$M47*100,IF($H47="Stock",$M47*$N47,"")))) | U47: =IF(OR($A47="",$C47<>"Closed",$D47="",$E47="",$T47=0),"",$R47/$T47*365/MAX(1,$E47-$D47)) | V47: Open FIVN $25 8/21 calls per joint CSV. | W47: Broker CSV
A48: 50 | B48: Long Call/Put | C48: Open | D48: 46182 | F48: =IF($E48="","",DATE(YEAR($E48),MONTH($E48),1)) | G48: FIVN | H48: Option | I48: Buy | J48: Call | K48: 22.5 | L48: 46402 | M48: 1 | N48: 5.5 | O48: 5.5 | P48: 0 | Q48: =IF($A48="","",IF($H48="Stock",IF($I48="Buy",-$M48*$N48-$P48,IF($I48="Sell",IF($N48="", $M48*$O48-$P48,($O48-$N48)*$M48-$P48),"")),IF($I48="Sell",($N48-IF($O48="",0,$O48))*$M48*100-$P48,IF($I48="Buy",(IF($O48="",0,$O48)-$N48)*$M48*100-$P48,"")))) | R48: =IF($A48="","",IF($C48="Open","",$Q48)) | S48: =IF($A48="","",IFS($B48="Covered Call","Covered Call Premium",$B48="Cash Secured Put","Cash Secured Put Premium",$B48="Long Call/Put","Long Call/Put P/L",$B48="Debit Spread","Long Call/Put P/L",$B48="Stock Sale","Stock Sales",TRUE,"Other")) | T48: =IF($A48="","",IF($B48="Cash Secured Put",$K48*$M48*100,IF($B48="Covered Call",$K48*$M48*100,IF($H48="Stock",$M48*$N48,"")))) | U48: =IF(OR($A48="",$C48<>"Closed",$D48="",$E48="",$T48=0),"",$R48/$T48*365/MAX(1,$E48-$D48)) | V48: Open FIVN $22.50 call per joint CSV. | W48: Broker CSV
A49: 55 | B49: Long Call/Put | C49: Open | D49: 46184 | F49: =IF($E49="","",DATE(YEAR($E49),MONTH($E49),1)) | G49: SHLS | H49: Option | I49: Buy | J49: Call | K49: 10 | L49: 46402 | M49: 2 | N49: 2.8 | O49: 2.8 | P49: 0 | Q49: =IF($A49="","",IF($H49="Stock",IF($I49="Buy",-$M49*$N49-$P49,IF($I49="Sell",IF($N49="", $M49*$O49-$P49,($O49-$N49)*$M49-$P49),"")),IF($I49="Sell",($N49-IF($O49="",0,$O49))*$M49*100-$P49,IF($I49="Buy",(IF($O49="",0,$O49)-$N49)*$M49*100-$P49,"")))) | R49: =IF($A49="","",IF($C49="Open","",$Q49)) | S49: =IF($A49="","",IFS($B49="Covered Call","Covered Call Premium",$B49="Cash Secured Put","Cash Secured Put Premium",$B49="Long Call/Put","Long Call/Put P/L",$B49="Debit Spread","Long Call/Put P/L",$B49="Stock Sale","Stock Sales",TRUE,"Other")) | T49: =IF($A49="","",IF($B49="Cash Secured Put",$K49*$M49*100,IF($B49="Covered Call",$K49*$M49*100,IF($H49="Stock",$M49*$N49,"")))) | U49: =IF(OR($A49="",$C49<>"Closed",$D49="",$E49="",$T49=0),"",$R49/$T49*365/MAX(1,$E49-$D49)) | V49: Bought 2 SHLS $10 calls expiring 2027-01-15 at $2.80 each on 2026-06-11. | W49: User trade update
A50: 16 | B50: Stock Sale | C50: Closed | D50: 46157 | E50: 46157 | F50: =IF($E50="","",DATE(YEAR($E50),MONTH($E50),1)) | G50: BMNR | H50: Stock | I50: Sell | M50: 50 | N50: 31.58 | O50: 20.25 | P50: 0 | Q50: =IF($A50="","",IF($H50="Stock",IF($I50="Buy",-$M50*$N50-$P50,IF($I50="Sell",IF($N50="", $M50*$O50-$P50,($O50-$N50)*$M50-$P50),"")),IF($I50="Sell",($N50-IF($O50="",0,$O50))*$M50*100-$P50,IF($I50="Buy",(IF($O50="",0,$O50)-$N50)*$M50*100-$P50,"")))) | R50: =IF($A50="","",IF($C50="Open","",$Q50)) | S50: =IF($A50="","",IFS($B50="Covered Call","Covered Call Premium",$B50="Cash Secured Put","Cash Secured Put Premium",$B50="Long Call/Put","Long Call/Put P/L",$B50="Debit Spread","Long Call/Put P/L",$B50="Stock Sale","Stock Sales",TRUE,"Other")) | T50: =IF($A50="","",IF($B50="Cash Secured Put",$K50*$M50*100,IF($B50="Covered Call",$K50*$M50*100,IF($H50="Stock",$M50*$N50,"")))) | U50: =IF(OR($A50="",$C50<>"Closed",$D50="",$E50="",$T50=0),"",$R50/$T50*365/MAX(1,$E50-$D50)) | V50: Sold 50 BMNR shares at $20.25 on 2026-05-15. Entry price uses current weighted average basis. | W50: User trade update
A51: 17 | B51: Stock Buy | C51: Closed | D51: 46157 | E51: 46170 | F51: =IF($E51="","",DATE(YEAR($E51),MONTH($E51),1)) | G51: FIVN | H51: Stock | I51: Buy | M51: 100 | N51: 21.83 | O51: 22.77 | P51: 0 | Q51: =IF($A51="","",IF($H51="Stock",IF($I51="Buy",-$M51*$N51-$P51,IF($I51="Sell",IF($N51="", $M51*$O51-$P51,($O51-$N51)*$M51-$P51),"")),IF($I51="Sell",($N51-IF($O51="",0,$O51))*$M51*100-$P51,IF($I51="Buy",(IF($O51="",0,$O51)-$N51)*$M51*100-$P51,"")))) | R51: =IF($A51="","",IF($C51="Open","",$Q51)) | S51: =IF($A51="","",IFS($B51="Covered Call","Covered Call Premium",$B51="Cash Secured Put","Cash Secured Put Premium",$B51="Long Call/Put","Long Call/Put P/L",$B51="Debit Spread","Long Call/Put P/L",$B51="Stock Sale","Stock Sales",TRUE,"Other")) | T51: =IF($A51="","",IF($B51="Cash Secured Put",$K51*$M51*100,IF($B51="Covered Call",$K51*$M51*100,IF($H51="Stock",$M51*$N51,"")))) | U51: =IF(OR($A51="",$C51<>"Closed",$D51="",$E51="",$T51=0),"",$R51/$T51*365/MAX(1,$E51-$D51)) | V51: Bought 100 FIVN shares 2026-05-15 and sold 2026-05-28; consolidated from prior tracker and joint CSV. | W51: Existing tracker + Broker CSV
A52: 18 | B52: Stock Sale | C52: Closed | D52: 46157 | E52: 46157 | F52: =IF($E52="","",DATE(YEAR($E52),MONTH($E52),1)) | G52: PLTR | H52: Stock | I52: Sell | M52: 10 | N52: 18.51 | O52: 132.2575 | P52: 0 | Q52: =IF($A52="","",IF($H52="Stock",IF($I52="Buy",-$M52*$N52-$P52,IF($I52="Sell",IF($N52="", $M52*$O52-$P52,($O52-$N52)*$M52-$P52),"")),IF($I52="Sell",($N52-IF($O52="",0,$O52))*$M52*100-$P52,IF($I52="Buy",(IF($O52="",0,$O52)-$N52)*$M52*100-$P52,"")))) | R52: =IF($A52="","",IF($C52="Open","",$Q52)) | S52: =IF($A52="","",IFS($B52="Covered Call","Covered Call Premium",$B52="Cash Secured Put","Cash Secured Put Premium",$B52="Long Call/Put","Long Call/Put P/L",$B52="Debit Spread","Long Call/Put P/L",$B52="Stock Sale","Stock Sales",TRUE,"Other")) | T52: =IF($A52="","",IF($B52="Cash Secured Put",$K52*$M52*100,IF($B52="Covered Call",$K52*$M52*100,IF($H52="Stock",$M52*$N52,"")))) | U52: =IF(OR($A52="",$C52<>"Closed",$D52="",$E52="",$T52=0),"",$R52/$T52*365/MAX(1,$E52-$D52)) | V52: Sold 10 PLTR shares on 2026-05-15. Sale price retained from prior tracker. | W52: Existing tracker
A53: 21 | B53: Stock Sale | C53: Closed | D53: 46161 | E53: 46161 | F53: =IF($E53="","",DATE(YEAR($E53),MONTH($E53),1)) | G53: PLTR | H53: Stock | I53: Sell | M53: 10 | N53: 18.51 | O53: 133.98 | P53: 0 | Q53: =IF($A53="","",IF($H53="Stock",IF($I53="Buy",-$M53*$N53-$P53,IF($I53="Sell",IF($N53="", $M53*$O53-$P53,($O53-$N53)*$M53-$P53),"")),IF($I53="Sell",($N53-IF($O53="",0,$O53))*$M53*100-$P53,IF($I53="Buy",(IF($O53="",0,$O53)-$N53)*$M53*100-$P53,"")))) | R53: =IF($A53="","",IF($C53="Open","",$Q53)) | S53: =IF($A53="","",IFS($B53="Covered Call","Covered Call Premium",$B53="Cash Secured Put","Cash Secured Put Premium",$B53="Long Call/Put","Long Call/Put P/L",$B53="Debit Spread","Long Call/Put P/L",$B53="Stock Sale","Stock Sales",TRUE,"Other")) | T53: =IF($A53="","",IF($B53="Cash Secured Put",$K53*$M53*100,IF($B53="Covered Call",$K53*$M53*100,IF($H53="Stock",$M53*$N53,"")))) | U53: =IF(OR($A53="",$C53<>"Closed",$D53="",$E53="",$T53=0),"",$R53/$T53*365/MAX(1,$E53-$D53)) | V53: Sold 10 PLTR shares at $133.98 on 2026-05-19. | W53: User trade update
A54: 33 | B54: Stock Sale | C54: Closed | D54: 46178 | E54: 46178 | F54: =IF($E54="","",DATE(YEAR($E54),MONTH($E54),1)) | G54: GRAB | H54: Stock | I54: Sell | M54: 4000 | N54: 5 | O54: 3.39 | P54: 1.06 | Q54: =IF($A54="","",IF($H54="Stock",IF($I54="Buy",-$M54*$N54-$P54,IF($I54="Sell",IF($N54="", $M54*$O54-$P54,($O54-$N54)*$M54-$P54),"")),IF($I54="Sell",($N54-IF($O54="",0,$O54))*$M54*100-$P54,IF($I54="Buy",(IF($O54="",0,$O54)-$N54)*$M54*100-$P54,"")))) | R54: =IF($A54="","",IF($C54="Open","",$Q54)) | S54: =IF($A54="","",IFS($B54="Covered Call","Covered Call Premium",$B54="Cash Secured Put","Cash Secured Put Premium",$B54="Long Call/Put","Long Call/Put P/L",$B54="Debit Spread","Long Call/Put P/L",$B54="Stock Sale","Stock Sales",TRUE,"Other")) | T54: =IF($A54="","",IF($B54="Cash Secured Put",$K54*$M54*100,IF($B54="Covered Call",$K54*$M54*100,IF($H54="Stock",$M54*$N54,"")))) | U54: =IF(OR($A54="",$C54<>"Closed",$D54="",$E54="",$T54=0),"",$R54/$T54*365/MAX(1,$E54-$D54)) | V54: Sold all 4,000 GRAB shares across three fills at $3.39 on 2026-06-05 per individual CSV. | W54: Broker CSV
A55: 34 | B55: Stock Buy | C55: Open | D55: 46163 | F55: =IF($E55="","",DATE(YEAR($E55),MONTH($E55),1)) | G55: NTNX | H55: Stock | I55: Buy | M55: 100 | N55: 45.35 | P55: 0 | Q55: =IF($A55="","",IF($H55="Stock",IF($I55="Buy",-$M55*$N55-$P55,IF($I55="Sell",IF($N55="", $M55*$O55-$P55,($O55-$N55)*$M55-$P55),"")),IF($I55="Sell",($N55-IF($O55="",0,$O55))*$M55*100-$P55,IF($I55="Buy",(IF($O55="",0,$O55)-$N55)*$M55*100-$P55,"")))) | R55: =IF($A55="","",IF($C55="Open","",$Q55)) | S55: =IF($A55="","",IFS($B55="Covered Call","Covered Call Premium",$B55="Cash Secured Put","Cash Secured Put Premium",$B55="Long Call/Put","Long Call/Put P/L",$B55="Debit Spread","Long Call/Put P/L",$B55="Stock Sale","Stock Sales",TRUE,"Other")) | T55: =IF($A55="","",IF($B55="Cash Secured Put",$K55*$M55*100,IF($B55="Covered Call",$K55*$M55*100,IF($H55="Stock",$M55*$N55,"")))) | U55: =IF(OR($A55="",$C55<>"Closed",$D55="",$E55="",$T55=0),"",$R55/$T55*365/MAX(1,$E55-$D55)) | V55: Bought 100 NTNX shares at $45.35 on 2026-05-21 per joint CSV. | W55: Broker CSV
A56: 51 | B56: Stock Sale | C56: Closed | D56: 46176 | E56: 46176 | F56: =IF($E56="","",DATE(YEAR($E56),MONTH($E56),1)) | G56: PLTR | H56: Stock | I56: Sell | M56: 10 | N56: 18.51 | O56: 144.4 | P56: 0 | Q56: =IF($A56="","",IF($H56="Stock",IF($I56="Buy",-$M56*$N56-$P56,IF($I56="Sell",IF($N56="", $M56*$O56-$P56,($O56-$N56)*$M56-$P56),"")),IF($I56="Sell",($N56-IF($O56="",0,$O56))*$M56*100-$P56,IF($I56="Buy",(IF($O56="",0,$O56)-$N56)*$M56*100-$P56,"")))) | R56: =IF($A56="","",IF($C56="Open","",$Q56)) | S56: =IF($A56="","",IFS($B56="Covered Call","Covered Call Premium",$B56="Cash Secured Put","Cash Secured Put Premium",$B56="Long Call/Put","Long Call/Put P/L",$B56="Debit Spread","Long Call/Put P/L",$B56="Stock Sale","Stock Sales",TRUE,"Other")) | T56: =IF($A56="","",IF($B56="Cash Secured Put",$K56*$M56*100,IF($B56="Covered Call",$K56*$M56*100,IF($H56="Stock",$M56*$N56,"")))) | U56: =IF(OR($A56="",$C56<>"Closed",$D56="",$E56="",$T56=0),"",$R56/$T56*365/MAX(1,$E56-$D56)) | V56: Sold 10 PLTR shares at $144.40 on 2026-06-03 per joint CSV. | W56: Broker CSV
A57: 52 | B57: Stock Buy | C57: Open | D57: 46181 | F57: =IF($E57="","",DATE(YEAR($E57),MONTH($E57),1)) | G57: ADEA | H57: Stock | I57: Buy | M57: 100 | N57: 29.69 | P57: 0 | Q57: =IF($A57="","",IF($H57="Stock",IF($I57="Buy",-$M57*$N57-$P57,IF($I57="Sell",IF($N57="", $M57*$O57-$P57,($O57-$N57)*$M57-$P57),"")),IF($I57="Sell",($N57-IF($O57="",0,$O57))*$M57*100-$P57,IF($I57="Buy",(IF($O57="",0,$O57)-$N57)*$M57*100-$P57,"")))) | R57: =IF($A57="","",IF($C57="Open","",$Q57)) | S57: =IF($A57="","",IFS($B57="Covered Call","Covered Call Premium",$B57="Cash Secured Put","Cash Secured Put Premium",$B57="Long Call/Put","Long Call/Put P/L",$B57="Debit Spread","Long Call/Put P/L",$B57="Stock Sale","Stock Sales",TRUE,"Other")) | T57: =IF($A57="","",IF($B57="Cash Secured Put",$K57*$M57*100,IF($B57="Covered Call",$K57*$M57*100,IF($H57="Stock",$M57*$N57,"")))) | U57: =IF(OR($A57="",$C57<>"Closed",$D57="",$E57="",$T57=0),"",$R57/$T57*365/MAX(1,$E57-$D57)) | V57: Bought 100 ADEA shares at $29.69 on 2026-06-08 per joint CSV. | W57: Broker CSV
A58: 53 | B58: Stock Buy | C58: Open | D58: 46178 | F58: =IF($E58="","",DATE(YEAR($E58),MONTH($E58),1)) | G58: CRWV | H58: Stock | I58: Buy | M58: 100 | N58: 102.43 | P58: 0 | Q58: =IF($A58="","",IF($H58="Stock",IF($I58="Buy",-$M58*$N58-$P58,IF($I58="Sell",IF($N58="", $M58*$O58-$P58,($O58-$N58)*$M58-$P58),"")),IF($I58="Sell",($N58-IF($O58="",0,$O58))*$M58*100-$P58,IF($I58="Buy",(IF($O58="",0,$O58)-$N58)*$M58*100-$P58,"")))) | R58: =IF($A58="","",IF($C58="Open","",$Q58)) | S58: =IF($A58="","",IFS($B58="Covered Call","Covered Call Premium",$B58="Cash Secured Put","Cash Secured Put Premium",$B58="Long Call/Put","Long Call/Put P/L",$B58="Debit Spread","Long Call/Put P/L",$B58="Stock Sale","Stock Sales",TRUE,"Other")) | T58: =IF($A58="","",IF($B58="Cash Secured Put",$K58*$M58*100,IF($B58="Covered Call",$K58*$M58*100,IF($H58="Stock",$M58*$N58,"")))) | U58: =IF(OR($A58="",$C58<>"Closed",$D58="",$E58="",$T58=0),"",$R58/$T58*365/MAX(1,$E58-$D58)) | V58: Bought 50 CRWV at $103.07 and 50 at $101.79 on 2026-06-05 per individual CSV; weighted average $102.43. | W58: Broker CSV
A59: 54 | B59: Stock Buy | C59: Open | D59: 46182 | F59: =IF($E59="","",DATE(YEAR($E59),MONTH($E59),1)) | G59: FIVN | H59: Stock | I59: Buy | M59: 100 | N59: 23 | P59: 0 | Q59: =IF($A59="","",IF($H59="Stock",IF($I59="Buy",-$M59*$N59-$P59,IF($I59="Sell",IF($N59="", $M59*$O59-$P59,($O59-$N59)*$M59-$P59),"")),IF($I59="Sell",($N59-IF($O59="",0,$O59))*$M59*100-$P59,IF($I59="Buy",(IF($O59="",0,$O59)-$N59)*$M59*100-$P59,"")))) | R59: =IF($A59="","",IF($C59="Open","",$Q59)) | S59: =IF($A59="","",IFS($B59="Covered Call","Covered Call Premium",$B59="Cash Secured Put","Cash Secured Put Premium",$B59="Long Call/Put","Long Call/Put P/L",$B59="Debit Spread","Long Call/Put P/L",$B59="Stock Sale","Stock Sales",TRUE,"Other")) | T59: =IF($A59="","",IF($B59="Cash Secured Put",$K59*$M59*100,IF($B59="Covered Call",$K59*$M59*100,IF($H59="Stock",$M59*$N59,"")))) | U59: =IF(OR($A59="",$C59<>"Closed",$D59="",$E59="",$T59=0),"",$R59/$T59*365/MAX(1,$E59-$D59)) | V59: Bought 100 FIVN shares at $23.00 on 2026-06-09 per joint CSV. | W59: Broker CSV
F60: =IF($E60="","",DATE(YEAR($E60),MONTH($E60),1)) | Q60: =IF($A60="","",IF($H60="Stock",IF($I60="Buy",-$M60*$N60-$P60,IF($I60="Sell",IF($N60="", $M60*$O60-$P60,($O60-$N60)*$M60-$P60),"")),IF($I60="Sell",($N60-IF($O60="",0,$O60))*$M60*100-$P60,IF($I60="Buy",(IF($O60="",0,$O60)-$N60)*$M60*100-$P60,"")))) | R60: =IF($A60="","",IF($C60="Open","",$Q60)) | S60: =IF($A60="","",IFS($B60="Covered Call","Covered Call Premium",$B60="Cash Secured Put","Cash Secured Put Premium",$B60="Long Call/Put","Long Call/Put P/L",$B60="Debit Spread","Long Call/Put P/L",$B60="Stock Sale","Stock Sales",TRUE,"Other")) | T60: =IF($A60="","",IF($B60="Cash Secured Put",$K60*$M60*100,IF($B60="Covered Call",$K60*$M60*100,IF($H60="Stock",$M60*$N60,"")))) | U60: =IF(OR($A60="",$C60<>"Closed",$D60="",$E60="",$T60=0),"",$R60/$T60*365/MAX(1,$E60-$D60))
F61: =IF($E61="","",DATE(YEAR($E61),MONTH($E61),1)) | Q61: =IF($A61="","",IF($H61="Stock",IF($I61="Buy",-$M61*$N61-$P61,IF($I61="Sell",IF($N61="", $M61*$O61-$P61,($O61-$N61)*$M61-$P61),"")),IF($I61="Sell",($N61-IF($O61="",0,$O61))*$M61*100-$P61,IF($I61="Buy",(IF($O61="",0,$O61)-$N61)*$M61*100-$P61,"")))) | R61: =IF($A61="","",IF($C61="Open","",$Q61)) | S61: =IF($A61="","",IFS($B61="Covered Call","Covered Call Premium",$B61="Cash Secured Put","Cash Secured Put Premium",$B61="Long Call/Put","Long Call/Put P/L",$B61="Debit Spread","Long Call/Put P/L",$B61="Stock Sale","Stock Sales",TRUE,"Other")) | T61: =IF($A61="","",IF($B61="Cash Secured Put",$K61*$M61*100,IF($B61="Covered Call",$K61*$M61*100,IF($H61="Stock",$M61*$N61,"")))) | U61: =IF(OR($A61="",$C61<>"Closed",$D61="",$E61="",$T61=0),"",$R61/$T61*365/MAX(1,$E61-$D61))
F62: =IF($E62="","",DATE(YEAR($E62),MONTH($E62),1)) | Q62: =IF($A62="","",IF($H62="Stock",IF($I62="Buy",-$M62*$N62-$P62,IF($I62="Sell",IF($N62="", $M62*$O62-$P62,($O62-$N62)*$M62-$P62),"")),IF($I62="Sell",($N62-IF($O62="",0,$O62))*$M62*100-$P62,IF($I62="Buy",(IF($O62="",0,$O62)-$N62)*$M62*100-$P62,"")))) | R62: =IF($A62="","",IF($C62="Open","",$Q62)) | S62: =IF($A62="","",IFS($B62="Covered Call","Covered Call Premium",$B62="Cash Secured Put","Cash Secured Put Premium",$B62="Long Call/Put","Long Call/Put P/L",$B62="Debit Spread","Long Call/Put P/L",$B62="Stock Sale","Stock Sales",TRUE,"Other")) | T62: =IF($A62="","",IF($B62="Cash Secured Put",$K62*$M62*100,IF($B62="Covered Call",$K62*$M62*100,IF($H62="Stock",$M62*$N62,"")))) | U62: =IF(OR($A62="",$C62<>"Closed",$D62="",$E62="",$T62=0),"",$R62/$T62*365/MAX(1,$E62-$D62))
F63: =IF($E63="","",DATE(YEAR($E63),MONTH($E63),1)) | Q63: =IF($A63="","",IF($H63="Stock",IF($I63="Buy",-$M63*$N63-$P63,IF($I63="Sell",IF($N63="", $M63*$O63-$P63,($O63-$N63)*$M63-$P63),"")),IF($I63="Sell",($N63-IF($O63="",0,$O63))*$M63*100-$P63,IF($I63="Buy",(IF($O63="",0,$O63)-$N63)*$M63*100-$P63,"")))) | R63: =IF($A63="","",IF($C63="Open","",$Q63)) | S63: =IF($A63="","",IFS($B63="Covered Call","Covered Call Premium",$B63="Cash Secured Put","Cash Secured Put Premium",$B63="Long Call/Put","Long Call/Put P/L",$B63="Debit Spread","Long Call/Put P/L",$B63="Stock Sale","Stock Sales",TRUE,"Other")) | T63: =IF($A63="","",IF($B63="Cash Secured Put",$K63*$M63*100,IF($B63="Covered Call",$K63*$M63*100,IF($H63="Stock",$M63*$N63,"")))) | U63: =IF(OR($A63="",$C63<>"Closed",$D63="",$E63="",$T63=0),"",$R63/$T63*365/MAX(1,$E63-$D63))
F64: =IF($E64="","",DATE(YEAR($E64),MONTH($E64),1)) | Q64: =IF($A64="","",IF($H64="Stock",IF($I64="Buy",-$M64*$N64-$P64,IF($I64="Sell",IF($N64="", $M64*$O64-$P64,($O64-$N64)*$M64-$P64),"")),IF($I64="Sell",($N64-IF($O64="",0,$O64))*$M64*100-$P64,IF($I64="Buy",(IF($O64="",0,$O64)-$N64)*$M64*100-$P64,"")))) | R64: =IF($A64="","",IF($C64="Open","",$Q64)) | S64: =IF($A64="","",IFS($B64="Covered Call","Covered Call Premium",$B64="Cash Secured Put","Cash Secured Put Premium",$B64="Long Call/Put","Long Call/Put P/L",$B64="Debit Spread","Long Call/Put P/L",$B64="Stock Sale","Stock Sales",TRUE,"Other")) | T64: =IF($A64="","",IF($B64="Cash Secured Put",$K64*$M64*100,IF($B64="Covered Call",$K64*$M64*100,IF($H64="Stock",$M64*$N64,"")))) | U64: =IF(OR($A64="",$C64<>"Closed",$D64="",$E64="",$T64=0),"",$R64/$T64*365/MAX(1,$E64-$D64))
F65: =IF($E65="","",DATE(YEAR($E65),MONTH($E65),1)) | Q65: =IF($A65="","",IF($H65="Stock",IF($I65="Buy",-$M65*$N65-$P65,IF($I65="Sell",IF($N65="", $M65*$O65-$P65,($O65-$N65)*$M65-$P65),"")),IF($I65="Sell",($N65-IF($O65="",0,$O65))*$M65*100-$P65,IF($I65="Buy",(IF($O65="",0,$O65)-$N65)*$M65*100-$P65,"")))) | R65: =IF($A65="","",IF($C65="Open","",$Q65)) | S65: =IF($A65="","",IFS($B65="Covered Call","Covered Call Premium",$B65="Cash Secured Put","Cash Secured Put Premium",$B65="Long Call/Put","Long Call/Put P/L",$B65="Debit Spread","Long Call/Put P/L",$B65="Stock Sale","Stock Sales",TRUE,"Other")) | T65: =IF($A65="","",IF($B65="Cash Secured Put",$K65*$M65*100,IF($B65="Covered Call",$K65*$M65*100,IF($H65="Stock",$M65*$N65,"")))) | U65: =IF(OR($A65="",$C65<>"Closed",$D65="",$E65="",$T65=0),"",$R65/$T65*365/MAX(1,$E65-$D65))
F66: =IF($E66="","",DATE(YEAR($E66),MONTH($E66),1)) | Q66: =IF($A66="","",IF($H66="Stock",IF($I66="Buy",-$M66*$N66-$P66,IF($I66="Sell",IF($N66="", $M66*$O66-$P66,($O66-$N66)*$M66-$P66),"")),IF($I66="Sell",($N66-IF($O66="",0,$O66))*$M66*100-$P66,IF($I66="Buy",(IF($O66="",0,$O66)-$N66)*$M66*100-$P66,"")))) | R66: =IF($A66="","",IF($C66="Open","",$Q66)) | S66: =IF($A66="","",IFS($B66="Covered Call","Covered Call Premium",$B66="Cash Secured Put","Cash Secured Put Premium",$B66="Long Call/Put","Long Call/Put P/L",$B66="Debit Spread","Long Call/Put P/L",$B66="Stock Sale","Stock Sales",TRUE,"Other")) | T66: =IF($A66="","",IF($B66="Cash Secured Put",$K66*$M66*100,IF($B66="Covered Call",$K66*$M66*100,IF($H66="Stock",$M66*$N66,"")))) | U66: =IF(OR($A66="",$C66<>"Closed",$D66="",$E66="",$T66=0),"",$R66/$T66*365/MAX(1,$E66-$D66))
F67: =IF($E67="","",DATE(YEAR($E67),MONTH($E67),1)) | Q67: =IF($A67="","",IF($H67="Stock",IF($I67="Buy",-$M67*$N67-$P67,IF($I67="Sell",IF($N67="", $M67*$O67-$P67,($O67-$N67)*$M67-$P67),"")),IF($I67="Sell",($N67-IF($O67="",0,$O67))*$M67*100-$P67,IF($I67="Buy",(IF($O67="",0,$O67)-$N67)*$M67*100-$P67,"")))) | R67: =IF($A67="","",IF($C67="Open","",$Q67)) | S67: =IF($A67="","",IFS($B67="Covered Call","Covered Call Premium",$B67="Cash Secured Put","Cash Secured Put Premium",$B67="Long Call/Put","Long Call/Put P/L",$B67="Debit Spread","Long Call/Put P/L",$B67="Stock Sale","Stock Sales",TRUE,"Other")) | T67: =IF($A67="","",IF($B67="Cash Secured Put",$K67*$M67*100,IF($B67="Covered Call",$K67*$M67*100,IF($H67="Stock",$M67*$N67,"")))) | U67: =IF(OR($A67="",$C67<>"Closed",$D67="",$E67="",$T67=0),"",$R67/$T67*365/MAX(1,$E67-$D67))
F68: =IF($E68="","",DATE(YEAR($E68),MONTH($E68),1)) | Q68: =IF($A68="","",IF($H68="Stock",IF($I68="Buy",-$M68*$N68-$P68,IF($I68="Sell",IF($N68="", $M68*$O68-$P68,($O68-$N68)*$M68-$P68),"")),IF($I68="Sell",($N68-IF($O68="",0,$O68))*$M68*100-$P68,IF($I68="Buy",(IF($O68="",0,$O68)-$N68)*$M68*100-$P68,"")))) | R68: =IF($A68="","",IF($C68="Open","",$Q68)) | S68: =IF($A68="","",IFS($B68="Covered Call","Covered Call Premium",$B68="Cash Secured Put","Cash Secured Put Premium",$B68="Long Call/Put","Long Call/Put P/L",$B68="Debit Spread","Long Call/Put P/L",$B68="Stock Sale","Stock Sales",TRUE,"Other")) | T68: =IF($A68="","",IF($B68="Cash Secured Put",$K68*$M68*100,IF($B68="Covered Call",$K68*$M68*100,IF($H68="Stock",$M68*$N68,"")))) | U68: =IF(OR($A68="",$C68<>"Closed",$D68="",$E68="",$T68=0),"",$R68/$T68*365/MAX(1,$E68-$D68))
F69: =IF($E69="","",DATE(YEAR($E69),MONTH($E69),1)) | Q69: =IF($A69="","",IF($H69="Stock",IF($I69="Buy",-$M69*$N69-$P69,IF($I69="Sell",IF($N69="", $M69*$O69-$P69,($O69-$N69)*$M69-$P69),"")),IF($I69="Sell",($N69-IF($O69="",0,$O69))*$M69*100-$P69,IF($I69="Buy",(IF($O69="",0,$O69)-$N69)*$M69*100-$P69,"")))) | R69: =IF($A69="","",IF($C69="Open","",$Q69)) | S69: =IF($A69="","",IFS($B69="Covered Call","Covered Call Premium",$B69="Cash Secured Put","Cash Secured Put Premium",$B69="Long Call/Put","Long Call/Put P/L",$B69="Debit Spread","Long Call/Put P/L",$B69="Stock Sale","Stock Sales",TRUE,"Other")) | T69: =IF($A69="","",IF($B69="Cash Secured Put",$K69*$M69*100,IF($B69="Covered Call",$K69*$M69*100,IF($H69="Stock",$M69*$N69,"")))) | U69: =IF(OR($A69="",$C69<>"Closed",$D69="",$E69="",$T69=0),"",$R69/$T69*365/MAX(1,$E69-$D69))
F70: =IF($E70="","",DATE(YEAR($E70),MONTH($E70),1)) | Q70: =IF($A70="","",IF($H70="Stock",IF($I70="Buy",-$M70*$N70-$P70,IF($I70="Sell",IF($N70="", $M70*$O70-$P70,($O70-$N70)*$M70-$P70),"")),IF($I70="Sell",($N70-IF($O70="",0,$O70))*$M70*100-$P70,IF($I70="Buy",(IF($O70="",0,$O70)-$N70)*$M70*100-$P70,"")))) | R70: =IF($A70="","",IF($C70="Open","",$Q70)) | S70: =IF($A70="","",IFS($B70="Covered Call","Covered Call Premium",$B70="Cash Secured Put","Cash Secured Put Premium",$B70="Long Call/Put","Long Call/Put P/L",$B70="Debit Spread","Long Call/Put P/L",$B70="Stock Sale","Stock Sales",TRUE,"Other")) | T70: =IF($A70="","",IF($B70="Cash Secured Put",$K70*$M70*100,IF($B70="Covered Call",$K70*$M70*100,IF($H70="Stock",$M70*$N70,"")))) | U70: =IF(OR($A70="",$C70<>"Closed",$D70="",$E70="",$T70=0),"",$R70/$T70*365/MAX(1,$E70-$D70))
F71: =IF($E71="","",DATE(YEAR($E71),MONTH($E71),1)) | Q71: =IF($A71="","",IF($H71="Stock",IF($I71="Buy",-$M71*$N71-$P71,IF($I71="Sell",IF($N71="", $M71*$O71-$P71,($O71-$N71)*$M71-$P71),"")),IF($I71="Sell",($N71-IF($O71="",0,$O71))*$M71*100-$P71,IF($I71="Buy",(IF($O71="",0,$O71)-$N71)*$M71*100-$P71,"")))) | R71: =IF($A71="","",IF($C71="Open","",$Q71)) | S71: =IF($A71="","",IFS($B71="Covered Call","Covered Call Premium",$B71="Cash Secured Put","Cash Secured Put Premium",$B71="Long Call/Put","Long Call/Put P/L",$B71="Debit Spread","Long Call/Put P/L",$B71="Stock Sale","Stock Sales",TRUE,"Other")) | T71: =IF($A71="","",IF($B71="Cash Secured Put",$K71*$M71*100,IF($B71="Covered Call",$K71*$M71*100,IF($H71="Stock",$M71*$N71,"")))) | U71: =IF(OR($A71="",$C71<>"Closed",$D71="",$E71="",$T71=0),"",$R71/$T71*365/MAX(1,$E71-$D71))
... F1004: =IF($E1004="","",DATE(YEAR($E1004),MONTH($E1004),1)) | Q1004: =IF($A1004="","",IF($H1004="Stock",IF($I1004="Buy",-$M1004*$N1004-$P1004,IF($I1004="Sell",IF($N1004="", $M1004*$O1004-$P1004,($O1004-$N1004)*$M1004-$P1004),"")),IF($I1004="Sell",($N1004-IF($O1004="",0,$O1004))*$M1004*100-$P1004,IF($I1004="Buy",(IF($O1004="",0,$O1004)-$N1004)*$M1004*100-$P1004,"")))) | R1004: =IF($A1004="","",IF($C1004="Open","",$Q1004)) | S1004: =IF($A1004="","",IFS($B1004="Covered Call","Covered Call Premium",$B1004="Cash Secured Put","Cash Secured Put Premium",$B1004="Long Call/Put","Long Call/Put P/L",$B1004="Debit Spread","Long Call/Put P/L",$B1004="Stock Sale","Stock Sales",TRUE,"Other")) | T1004: =IF($A1004="","",IF($B1004="Cash Secured Put",$K1004*$M1004*100,IF($B1004="Covered Call",$K1004*$M1004*100,IF($H1004="Stock",$M1004*$N1004,"")))) | U1004: =IF(OR($A1004="",$C1004<>"Closed",$D1004="",$E1004="",$T1004=0),"",$R1004/$T1004*365/MAX(1,$E1004-$D1004))

Sheet Options Positions
A1: Current Options Positions
A2: Open option positions from Robinhood screenshots. Positive quantity/market value indicates long exposure; negative market value indicates short option liability.
A4: Ticker | B4: Structure | C4: Long/Short | D4: Contracts / Qty | E4: Option Type | F4: Strike / Lower Strike | G4: Upper Strike | H4: Expiration | I4: Open Date | J4: Avg Credit / Cost | K4: Current Price | L4: Original Premium / Cost | M4: Current Market Value | N4: Unrealized P/L | O4: Cash-Secured Obligation | P4: Covered Shares Used | Q4: Notes | R4: Source
A5: LUMN | B5: Put 11 | C5: Short | D5: -1 | E5: Put | F5: 11 | H5: 46185 | I5: 46156 | J5: 1.02 | K5: 1.35 | L5: =IF($A5="","",ABS($D5)*$J5*100) | M5: =IF($A5="","",IF($C5="Short",-ABS($D5)*$K5*100,ABS($D5)*$K5*100)) | N5: =IF($A5="","",IF($C5="Short",($J5-$K5)*ABS($D5)*100,($K5-$J5)*ABS($D5)*100)) | O5: =IF(AND($C5="Short",$E5="Put"),ABS($D5)*$F5*100,0) | P5: =IF($A5="",0,0) | Q5: Open position retained from tracker; not present in YTD CSV exports. | R5: Existing tracker
A6: GRAB | B6: Call Debit Spread | C6: Long | D6: 180 | E6: Call | F6: 10 | G6: 12 | H6: 46773 | I6: 46051 | J6: 0.1 | K6: 0.08 | L6: =IF($A6="","",ABS($D6)*$J6*100) | M6: =IF($A6="","",IF($C6="Short",-ABS($D6)*$K6*100,ABS($D6)*$K6*100)) | N6: =IF($A6="","",IF($C6="Short",($J6-$K6)*ABS($D6)*100,($K6-$J6)*ABS($D6)*100)) | O6: =IF(AND($C6="Short",$E6="Put"),ABS($D6)*$F6*100,0) | P6: =IF($A6="",0,0) | Q6: Open GRAB $10/$12 call debit spread; YTD CSV confirms 180 paired contracts. | R6: Broker CSV + existing tracker
A7: PLTR | B7: Call 190 | C7: Short | D7: -1 | E7: Call | F7: 190 | H7: 46402 | I7: 46129 | J7: 14.73 | K7: 9.38 | L7: =IF($A7="","",ABS($D7)*$J7*100) | M7: =IF($A7="","",IF($C7="Short",-ABS($D7)*$K7*100,ABS($D7)*$K7*100)) | N7: =IF($A7="","",IF($C7="Short",($J7-$K7)*ABS($D7)*100,($K7-$J7)*ABS($D7)*100)) | O7: =IF(AND($C7="Short",$E7="Put"),ABS($D7)*$F7*100,0) | P7: =IF($A7="",0,ABS($D7)*100) | Q7: Open PLTR $190 covered call per individual CSV. | R7: Broker CSV
A8: GRAB | B8: Call Debit Spread | C8: Long | D8: 400 | E8: Call | F8: 7.5 | G8: 10 | H8: 46402 | I8: 45681 | J8: 0.29 | K8: 0.03 | L8: =IF($A8="","",ABS($D8)*$J8*100) | M8: =IF($A8="","",IF($C8="Short",-ABS($D8)*$K8*100,ABS($D8)*$K8*100)) | N8: =IF($A8="","",IF($C8="Short",($J8-$K8)*ABS($D8)*100,($K8-$J8)*ABS($D8)*100)) | O8: =IF(AND($C8="Short",$E8="Put"),ABS($D8)*$F8*100,0) | P8: =IF($A8="",0,0) | Q8: Consolidated GRAB $7.50/$10 call debit spreads. Existing tracker keeps pre-2026 contracts; CSV confirms 60 YTD additions. | R8: Existing tracker + Broker CSV
A9: BMNR | B9: Call 75 | C9: Long | D9: 1 | E9: Call | F9: 75 | H9: 46191 | I9: 45989 | J9: 4.75 | K9: 0.02 | L9: =IF($A9="","",ABS($D9)*$J9*100) | M9: =IF($A9="","",IF($C9="Short",-ABS($D9)*$K9*100,ABS($D9)*$K9*100)) | N9: =IF($A9="","",IF($C9="Short",($J9-$K9)*ABS($D9)*100,($K9-$J9)*ABS($D9)*100)) | O9: =IF(AND($C9="Short",$E9="Put"),ABS($D9)*$F9*100,0) | P9: =IF($A9="",0,0) | Q9: Long BMNR $75 call retained from tracker; opened before CSV period. | R9: Existing tracker
A10: NTNX | B10: Call 47.5 | C10: Long | D10: 2 | E10: Call | F10: 47.5 | H10: 46311 | I10: 46160 | J10: 7.15 | K10: 7.15 | L10: =IF($A10="","",ABS($D10)*$J10*100) | M10: =IF($A10="","",IF($C10="Short",-ABS($D10)*$K10*100,ABS($D10)*$K10*100)) | N10: =IF($A10="","",IF($C10="Short",($J10-$K10)*ABS($D10)*100,($K10-$J10)*ABS($D10)*100)) | O10: =IF(AND($C10="Short",$E10="Put"),ABS($D10)*$F10*100,0) | P10: =IF($A10="",0,0) | Q10: Bought 1 at $7.30 and 1 at $7.00 per joint CSV; average $7.15. | R10: Broker CSV
A11: PLTR | B11: Call 160 | C11: Short | D11: -1 | E11: Call | F11: 160 | H11: 46191 | I11: 46170 | J11: 0.98 | K11: 0.98 | L11: =IF($A11="","",ABS($D11)*$J11*100) | M11: =IF($A11="","",IF($C11="Short",-ABS($D11)*$K11*100,ABS($D11)*$K11*100)) | N11: =IF($A11="","",IF($C11="Short",($J11-$K11)*ABS($D11)*100,($K11-$J11)*ABS($D11)*100)) | O11: =IF(AND($C11="Short",$E11="Put"),ABS($D11)*$F11*100,0) | P11: =IF($A11="",0,ABS($D11)*100) | Q11: Open PLTR $160 covered call per joint CSV. | R11: Broker CSV
A12: SOFI | B12: Put 18 | C12: Short | D12: -1 | E12: Put | F12: 18 | H12: 46191 | I12: 46170 | J12: 1.49 | K12: 1.49 | L12: =IF($A12="","",ABS($D12)*$J12*100) | M12: =IF($A12="","",IF($C12="Short",-ABS($D12)*$K12*100,ABS($D12)*$K12*100)) | N12: =IF($A12="","",IF($C12="Short",($J12-$K12)*ABS($D12)*100,($K12-$J12)*ABS($D12)*100)) | O12: =IF(AND($C12="Short",$E12="Put"),ABS($D12)*$F12*100,0) | P12: =IF($A12="",0,0) | Q12: Open SOFI $18 put per joint CSV; corrected credit to $1.49. | R12: Broker CSV
A13: AEHR | B13: Call 160 | C13: Short | D13: -1 | E13: Call | F13: 160 | H13: 46205 | I13: 46170 | J13: 4.05 | K13: 4.05 | L13: =IF($A13="","",ABS($D13)*$J13*100) | M13: =IF($A13="","",IF($C13="Short",-ABS($D13)*$K13*100,ABS($D13)*$K13*100)) | N13: =IF($A13="","",IF($C13="Short",($J13-$K13)*ABS($D13)*100,($K13-$J13)*ABS($D13)*100)) | O13: =IF(AND($C13="Short",$E13="Put"),ABS($D13)*$F13*100,0) | P13: =IF($A13="",0,ABS($D13)*100) | Q13: Open AEHR $160 7/2 covered call per individual CSV. | R13: Broker CSV
A14: FIVN | B14: Call 25 | C14: Long | D14: 2 | E14: Call | F14: 25 | H14: 46311 | I14: 46170 | J14: 4.3 | K14: 4.3 | L14: =IF($A14="","",ABS($D14)*$J14*100) | M14: =IF($A14="","",IF($C14="Short",-ABS($D14)*$K14*100,ABS($D14)*$K14*100)) | N14: =IF($A14="","",IF($C14="Short",($J14-$K14)*ABS($D14)*100,($K14-$J14)*ABS($D14)*100)) | O14: =IF(AND($C14="Short",$E14="Put"),ABS($D14)*$F14*100,0) | P14: =IF($A14="",0,0) | Q14: Open FIVN $25 calls per joint CSV. | R14: Broker CSV
A15: PLTR | B15: Call 220 | C15: Short | D15: -1 | E15: Call | F15: 220 | H15: 46402 | I15: 46171 | J15: 12.5 | K15: 12.5 | L15: =IF($A15="","",ABS($D15)*$J15*100) | M15: =IF($A15="","",IF($C15="Short",-ABS($D15)*$K15*100,ABS($D15)*$K15*100)) | N15: =IF($A15="","",IF($C15="Short",($J15-$K15)*ABS($D15)*100,($K15-$J15)*ABS($D15)*100)) | O15: =IF(AND($C15="Short",$E15="Put"),ABS($D15)*$F15*100,0) | P15: =IF($A15="",0,ABS($D15)*100) | Q15: Final open PLTR $220 covered call from 2026-05-29 roll sequence per joint CSV. | R15: Broker CSV
A16: CRNC | B16: Put 12 | C16: Short | D16: -2 | E16: Put | F16: 12 | H16: 46191 | I16: 46174 | J16: 1.05 | K16: 1.05 | L16: =IF($A16="","",ABS($D16)*$J16*100) | M16: =IF($A16="","",IF($C16="Short",-ABS($D16)*$K16*100,ABS($D16)*$K16*100)) | N16: =IF($A16="","",IF($C16="Short",($J16-$K16)*ABS($D16)*100,($K16-$J16)*ABS($D16)*100)) | O16: =IF(AND($C16="Short",$E16="Put"),ABS($D16)*$F16*100,0) | P16: =IF($A16="",0,0) | Q16: Open 2 CRNC $12 cash secured puts per joint CSV. | R16: Broker CSV
A17: CRNC | B17: Call 10 | C17: Long | D17: 6 | E17: Call | F17: 10 | H17: 46255 | I17: 46174 | J17: 3.83 | K17: 3.83 | L17: =IF($A17="","",ABS($D17)*$J17*100) | M17: =IF($A17="","",IF($C17="Short",-ABS($D17)*$K17*100,ABS($D17)*$K17*100)) | N17: =IF($A17="","",IF($C17="Short",($J17-$K17)*ABS($D17)*100,($K17-$J17)*ABS($D17)*100)) | O17: =IF(AND($C17="Short",$E17="Put"),ABS($D17)*$F17*100,0) | P17: =IF($A17="",0,0) | Q17: Open CRNC $10 calls: 2 at $4.10, 2 at $3.60, 2 at $3.80; weighted average about $3.83. | R17: Broker CSV
A18: AEHR | B18: Call 160 | C18: Short | D18: -1 | E18: Call | F18: 160 | H18: 46402 | I18: 46182 | J18: 22.05 | K18: 22.05 | L18: =IF($A18="","",ABS($D18)*$J18*100) | M18: =IF($A18="","",IF($C18="Short",-ABS($D18)*$K18*100,ABS($D18)*$K18*100)) | N18: =IF($A18="","",IF($C18="Short",($J18-$K18)*ABS($D18)*100,($K18-$J18)*ABS($D18)*100)) | O18: =IF(AND($C18="Short",$E18="Put"),ABS($D18)*$F18*100,0) | P18: =IF($A18="",0,ABS($D18)*100) | Q18: Open AEHR $160 1/15/27 covered call from roll per individual CSV. | R18: Broker CSV
A19: NEXT | B19: Put 8 | C19: Short | D19: -1 | E19: Put | F19: 8 | H19: 46191 | I19: 46164 | J19: 0.45 | K19: 0.45 | L19: =IF($A19="","",ABS($D19)*$J19*100) | M19: =IF($A19="","",IF($C19="Short",-ABS($D19)*$K19*100,ABS($D19)*$K19*100)) | N19: =IF($A19="","",IF($C19="Short",($J19-$K19)*ABS($D19)*100,($K19-$J19)*ABS($D19)*100)) | O19: =IF(AND($C19="Short",$E19="Put"),ABS($D19)*$F19*100,0) | P19: =IF($A19="",0,0) | Q19: Open NEXT $8 put per joint CSV. | R19: Broker CSV
A20: ADEA | B20: Put 30 | C20: Short | D20: -1 | E20: Put | F20: 30 | H20: 46220 | I20: 46182 | J20: 3.6 | K20: 3.6 | L20: =IF($A20="","",ABS($D20)*$J20*100) | M20: =IF($A20="","",IF($C20="Short",-ABS($D20)*$K20*100,ABS($D20)*$K20*100)) | N20: =IF($A20="","",IF($C20="Short",($J20-$K20)*ABS($D20)*100,($K20-$J20)*ABS($D20)*100)) | O20: =IF(AND($C20="Short",$E20="Put"),ABS($D20)*$F20*100,0) | P20: =IF($A20="",0,0) | Q20: Open ADEA $30 cash secured put per joint CSV. | R20: Broker CSV
A21: ADEA | B21: Call 30 | C21: Long | D21: 2 | E21: Call | F21: 30 | H21: 46283 | I21: 46178 | J21: 6.6 | K21: 6.6 | L21: =IF($A21="","",ABS($D21)*$J21*100) | M21: =IF($A21="","",IF($C21="Short",-ABS($D21)*$K21*100,ABS($D21)*$K21*100)) | N21: =IF($A21="","",IF($C21="Short",($J21-$K21)*ABS($D21)*100,($K21-$J21)*ABS($D21)*100)) | O21: =IF(AND($C21="Short",$E21="Put"),ABS($D21)*$F21*100,0) | P21: =IF($A21="",0,0) | Q21: Open ADEA $30 calls per individual CSV. | R21: Broker CSV
A22: GRAB | B22: Call 5 | C22: Long | D22: 40 | E22: Call | F22: 5 | H22: 46738 | I22: 46178 | J22: 0.59 | K22: 0.59 | L22: =IF($A22="","",ABS($D22)*$J22*100) | M22: =IF($A22="","",IF($C22="Short",-ABS($D22)*$K22*100,ABS($D22)*$K22*100)) | N22: =IF($A22="","",IF($C22="Short",($J22-$K22)*ABS($D22)*100,($K22-$J22)*ABS($D22)*100)) | O22: =IF(AND($C22="Short",$E22="Put"),ABS($D22)*$F22*100,0) | P22: =IF($A22="",0,0) | Q22: Open GRAB $5 calls per individual CSV. | R22: Broker CSV
A23: CRNC | B23: Call 15 | C23: Long | D23: 2 | E23: Call | F23: 15 | H23: 46402 | I23: 46176 | J23: 3.3 | K23: 3.3 | L23: =IF($A23="","",ABS($D23)*$J23*100) | M23: =IF($A23="","",IF($C23="Short",-ABS($D23)*$K23*100,ABS($D23)*$K23*100)) | N23: =IF($A23="","",IF($C23="Short",($J23-$K23)*ABS($D23)*100,($K23-$J23)*ABS($D23)*100)) | O23: =IF(AND($C23="Short",$E23="Put"),ABS($D23)*$F23*100,0) | P23: =IF($A23="",0,0) | Q23: Open CRNC $15 calls per joint CSV. | R23: Broker CSV
A24: FIVN | B24: Call 25 | C24: Long | D24: 2 | E24: Call | F24: 25 | H24: 46255 | I24: 46176 | J24: 4 | K24: 4 | L24: =IF($A24="","",ABS($D24)*$J24*100) | M24: =IF($A24="","",IF($C24="Short",-ABS($D24)*$K24*100,ABS($D24)*$K24*100)) | N24: =IF($A24="","",IF($C24="Short",($J24-$K24)*ABS($D24)*100,($K24-$J24)*ABS($D24)*100)) | O24: =IF(AND($C24="Short",$E24="Put"),ABS($D24)*$F24*100,0) | P24: =IF($A24="",0,0) | Q24: Open FIVN $25 8/21 calls per joint CSV. | R24: Broker CSV
A25: FIVN | B25: Call 22.5 | C25: Long | D25: 1 | E25: Call | F25: 22.5 | H25: 46402 | I25: 46182 | J25: 5.5 | K25: 5.5 | L25: =IF($A25="","",ABS($D25)*$J25*100) | M25: =IF($A25="","",IF($C25="Short",-ABS($D25)*$K25*100,ABS($D25)*$K25*100)) | N25: =IF($A25="","",IF($C25="Short",($J25-$K25)*ABS($D25)*100,($K25-$J25)*ABS($D25)*100)) | O25: =IF(AND($C25="Short",$E25="Put"),ABS($D25)*$F25*100,0) | P25: =IF($A25="",0,0) | Q25: Open FIVN $22.50 call per joint CSV. | R25: Broker CSV
A26: SHLS | B26: Call 10 | C26: Long | D26: 2 | E26: Call | F26: 10 | H26: 46402 | I26: 46184 | J26: 2.8 | K26: 2.8 | L26: =IF($A26="","",ABS($D26)*$J26*100) | M26: =IF($A26="","",IF($C26="Short",-ABS($D26)*$K26*100,ABS($D26)*$K26*100)) | N26: =IF($A26="","",IF($C26="Short",($J26-$K26)*ABS($D26)*100,($K26-$J26)*ABS($D26)*100)) | O26: =IF(AND($C26="Short",$E26="Put"),ABS($D26)*$F26*100,0) | P26: =IF($A26="",0,0) | Q26: Bought 2 SHLS $10 calls expiring 2027-01-15 at $2.80 each on 2026-06-11. | R26: User trade update
A29: Options Exposure Summary
A30: Net option market value | B30: =SUM(M5:M26)
A31: Open option unrealized P/L | B31: =SUM(N5:N26)
A32: Cash-secured put obligation | B32: =SUM(O5:O26)
A33: Covered shares committed | B33: =SUM(P5:P26)
A34: Long debit spread cost basis | B34: =SUMIFS(L5:L26,B5:B26,"Call Debit Spread")
A35: Long debit spread market value | B35: =SUMIFS(M5:M26,B5:B26,"Call Debit Spread")

Sheet Revenue Tracker
A1: Monthly Revenue Tracker
A2: Formula-driven view of realized gains/losses by month and income bucket.
A4: Month | B4: Covered Call Premium | C4: Cash Secured Put Premium | D4: Long Call/Put P/L | E4: Stock Sales | F4: Other | G4: Total Realized P/L | H4: Trade Count | I4: Avg P/L / Trade
A5: 46023 | B5: =SUMIFS('Trade Log'!$R$5:$R$1004,'Trade Log'!$F$5:$F$1004,$A5,'Trade Log'!$S$5:$S$1004,B$4) | C5: =SUMIFS('Trade Log'!$R$5:$R$1004,'Trade Log'!$F$5:$F$1004,$A5,'Trade Log'!$S$5:$S$1004,C$4) | D5: =SUMIFS('Trade Log'!$R$5:$R$1004,'Trade Log'!$F$5:$F$1004,$A5,'Trade Log'!$S$5:$S$1004,D$4) | E5: =SUMIFS('Trade Log'!$R$5:$R$1004,'Trade Log'!$F$5:$F$1004,$A5,'Trade Log'!$S$5:$S$1004,E$4) | F5: =SUMIFS('Trade Log'!$R$5:$R$1004,'Trade Log'!$F$5:$F$1004,$A5,'Trade Log'!$S$5:$S$1004,F$4) | G5: =SUM(B5:F5) | H5: =COUNTIFS('Trade Log'!$F$5:$F$1004,$A5,'Trade Log'!$R$5:$R$1004,"<>") | I5: =IF($H5=0,"",$G5/$H5)
A6: 46054 | B6: =SUMIFS('Trade Log'!$R$5:$R$1004,'Trade Log'!$F$5:$F$1004,$A6,'Trade Log'!$S$5:$S$1004,B$4) | C6: =SUMIFS('Trade Log'!$R$5:$R$1004,'Trade Log'!$F$5:$F$1004,$A6,'Trade Log'!$S$5:$S$1004,C$4) | D6: =SUMIFS('Trade Log'!$R$5:$R$1004,'Trade Log'!$F$5:$F$1004,$A6,'Trade Log'!$S$5:$S$1004,D$4) | E6: =SUMIFS('Trade Log'!$R$5:$R$1004,'Trade Log'!$F$5:$F$1004,$A6,'Trade Log'!$S$5:$S$1004,E$4) | F6: =SUMIFS('Trade Log'!$R$5:$R$1004,'Trade Log'!$F$5:$F$1004,$A6,'Trade Log'!$S$5:$S$1004,F$4) | G6: =SUM(B6:F6) | H6: =COUNTIFS('Trade Log'!$F$5:$F$1004,$A6,'Trade Log'!$R$5:$R$1004,"<>") | I6: =IF($H6=0,"",$G6/$H6)
A7: 46082 | B7: =SUMIFS('Trade Log'!$R$5:$R$1004,'Trade Log'!$F$5:$F$1004,$A7,'Trade Log'!$S$5:$S$1004,B$4) | C7: =SUMIFS('Trade Log'!$R$5:$R$1004,'Trade Log'!$F$5:$F$1004,$A7,'Trade Log'!$S$5:$S$1004,C$4) | D7: =SUMIFS('Trade Log'!$R$5:$R$1004,'Trade Log'!$F$5:$F$1004,$A7,'Trade Log'!$S$5:$S$1004,D$4) | E7: =SUMIFS('Trade Log'!$R$5:$R$1004,'Trade Log'!$F$5:$F$1004,$A7,'Trade Log'!$S$5:$S$1004,E$4) | F7: =SUMIFS('Trade Log'!$R$5:$R$1004,'Trade Log'!$F$5:$F$1004,$A7,'Trade Log'!$S$5:$S$1004,F$4) | G7: =SUM(B7:F7) | H7: =COUNTIFS('Trade Log'!$F$5:$F$1004,$A7,'Trade Log'!$R$5:$R$1004,"<>") | I7: =IF($H7=0,"",$G7/$H7)
A8: 46113 | B8: =SUMIFS('Trade Log'!$R$5:$R$1004,'Trade Log'!$F$5:$F$1004,$A8,'Trade Log'!$S$5:$S$1004,B$4) | C8: =SUMIFS('Trade Log'!$R$5:$R$1004,'Trade Log'!$F$5:$F$1004,$A8,'Trade Log'!$S$5:$S$1004,C$4) | D8: =SUMIFS('Trade Log'!$R$5:$R$1004,'Trade Log'!$F$5:$F$1004,$A8,'Trade Log'!$S$5:$S$1004,D$4) | E8: =SUMIFS('Trade Log'!$R$5:$R$1004,'Trade Log'!$F$5:$F$1004,$A8,'Trade Log'!$S$5:$S$1004,E$4) | F8: =SUMIFS('Trade Log'!$R$5:$R$1004,'Trade Log'!$F$5:$F$1004,$A8,'Trade Log'!$S$5:$S$1004,F$4) | G8: =SUM(B8:F8) | H8: =COUNTIFS('Trade Log'!$F$5:$F$1004,$A8,'Trade Log'!$R$5:$R$1004,"<>") | I8: =IF($H8=0,"",$G8/$H8)
A9: 46143 | B9: =SUMIFS('Trade Log'!$R$5:$R$1004,'Trade Log'!$F$5:$F$1004,$A9,'Trade Log'!$S$5:$S$1004,B$4) | C9: =SUMIFS('Trade Log'!$R$5:$R$1004,'Trade Log'!$F$5:$F$1004,$A9,'Trade Log'!$S$5:$S$1004,C$4) | D9: =SUMIFS('Trade Log'!$R$5:$R$1004,'Trade Log'!$F$5:$F$1004,$A9,'Trade Log'!$S$5:$S$1004,D$4) | E9: =SUMIFS('Trade Log'!$R$5:$R$1004,'Trade Log'!$F$5:$F$1004,$A9,'Trade Log'!$S$5:$S$1004,E$4) | F9: =SUMIFS('Trade Log'!$R$5:$R$1004,'Trade Log'!$F$5:$F$1004,$A9,'Trade Log'!$S$5:$S$1004,F$4) | G9: =SUM(B9:F9) | H9: =COUNTIFS('Trade Log'!$F$5:$F$1004,$A9,'Trade Log'!$R$5:$R$1004,"<>") | I9: =IF($H9=0,"",$G9/$H9)
A10: 46174 | B10: =SUMIFS('Trade Log'!$R$5:$R$1004,'Trade Log'!$F$5:$F$1004,$A10,'Trade Log'!$S$5:$S$1004,B$4) | C10: =SUMIFS('Trade Log'!$R$5:$R$1004,'Trade Log'!$F$5:$F$1004,$A10,'Trade Log'!$S$5:$S$1004,C$4) | D10: =SUMIFS('Trade Log'!$R$5:$R$1004,'Trade Log'!$F$5:$F$1004,$A10,'Trade Log'!$S$5:$S$1004,D$4) | E10: =SUMIFS('Trade Log'!$R$5:$R$1004,'Trade Log'!$F$5:$F$1004,$A10,'Trade Log'!$S$5:$S$1004,E$4) | F10: =SUMIFS('Trade Log'!$R$5:$R$1004,'Trade Log'!$F$5:$F$1004,$A10,'Trade Log'!$S$5:$S$1004,F$4) | G10: =SUM(B10:F10) | H10: =COUNTIFS('Trade Log'!$F$5:$F$1004,$A10,'Trade Log'!$R$5:$R$1004,"<>") | I10: =IF($H10=0,"",$G10/$H10)
A11: 46204 | B11: =SUMIFS('Trade Log'!$R$5:$R$1004,'Trade Log'!$F$5:$F$1004,$A11,'Trade Log'!$S$5:$S$1004,B$4) | C11: =SUMIFS('Trade Log'!$R$5:$R$1004,'Trade Log'!$F$5:$F$1004,$A11,'Trade Log'!$S$5:$S$1004,C$4) | D11: =SUMIFS('Trade Log'!$R$5:$R$1004,'Trade Log'!$F$5:$F$1004,$A11,'Trade Log'!$S$5:$S$1004,D$4) | E11: =SUMIFS('Trade Log'!$R$5:$R$1004,'Trade Log'!$F$5:$F$1004,$A11,'Trade Log'!$S$5:$S$1004,E$4) | F11: =SUMIFS('Trade Log'!$R$5:$R$1004,'Trade Log'!$F$5:$F$1004,$A11,'Trade Log'!$S$5:$S$1004,F$4) | G11: =SUM(B11:F11) | H11: =COUNTIFS('Trade Log'!$F$5:$F$1004,$A11,'Trade Log'!$R$5:$R$1004,"<>") | I11: =IF($H11=0,"",$G11/$H11)
A12: 46235 | B12: =SUMIFS('Trade Log'!$R$5:$R$1004,'Trade Log'!$F$5:$F$1004,$A12,'Trade Log'!$S$5:$S$1004,B$4) | C12: =SUMIFS('Trade Log'!$R$5:$R$1004,'Trade Log'!$F$5:$F$1004,$A12,'Trade Log'!$S$5:$S$1004,C$4) | D12: =SUMIFS('Trade Log'!$R$5:$R$1004,'Trade Log'!$F$5:$F$1004,$A12,'Trade Log'!$S$5:$S$1004,D$4) | E12: =SUMIFS('Trade Log'!$R$5:$R$1004,'Trade Log'!$F$5:$F$1004,$A12,'Trade Log'!$S$5:$S$1004,E$4) | F12: =SUMIFS('Trade Log'!$R$5:$R$1004,'Trade Log'!$F$5:$F$1004,$A12,'Trade Log'!$S$5:$S$1004,F$4) | G12: =SUM(B12:F12) | H12: =COUNTIFS('Trade Log'!$F$5:$F$1004,$A12,'Trade Log'!$R$5:$R$1004,"<>") | I12: =IF($H12=0,"",$G12/$H12)
A13: 46266 | B13: =SUMIFS('Trade Log'!$R$5:$R$1004,'Trade Log'!$F$5:$F$1004,$A13,'Trade Log'!$S$5:$S$1004,B$4) | C13: =SUMIFS('Trade Log'!$R$5:$R$1004,'Trade Log'!$F$5:$F$1004,$A13,'Trade Log'!$S$5:$S$1004,C$4) | D13: =SUMIFS('Trade Log'!$R$5:$R$1004,'Trade Log'!$F$5:$F$1004,$A13,'Trade Log'!$S$5:$S$1004,D$4) | E13: =SUMIFS('Trade Log'!$R$5:$R$1004,'Trade Log'!$F$5:$F$1004,$A13,'Trade Log'!$S$5:$S$1004,E$4) | F13: =SUMIFS('Trade Log'!$R$5:$R$1004,'Trade Log'!$F$5:$F$1004,$A13,'Trade Log'!$S$5:$S$1004,F$4) | G13: =SUM(B13:F13) | H13: =COUNTIFS('Trade Log'!$F$5:$F$1004,$A13,'Trade Log'!$R$5:$R$1004,"<>") | I13: =IF($H13=0,"",$G13/$H13)
A14: 46296 | B14: =SUMIFS('Trade Log'!$R$5:$R$1004,'Trade Log'!$F$5:$F$1004,$A14,'Trade Log'!$S$5:$S$1004,B$4) | C14: =SUMIFS('Trade Log'!$R$5:$R$1004,'Trade Log'!$F$5:$F$1004,$A14,'Trade Log'!$S$5:$S$1004,C$4) | D14: =SUMIFS('Trade Log'!$R$5:$R$1004,'Trade Log'!$F$5:$F$1004,$A14,'Trade Log'!$S$5:$S$1004,D$4) | E14: =SUMIFS('Trade Log'!$R$5:$R$1004,'Trade Log'!$F$5:$F$1004,$A14,'Trade Log'!$S$5:$S$1004,E$4) | F14: =SUMIFS('Trade Log'!$R$5:$R$1004,'Trade Log'!$F$5:$F$1004,$A14,'Trade Log'!$S$5:$S$1004,F$4) | G14: =SUM(B14:F14) | H14: =COUNTIFS('Trade Log'!$F$5:$F$1004,$A14,'Trade Log'!$R$5:$R$1004,"<>") | I14: =IF($H14=0,"",$G14/$H14)
A15: 46327 | B15: =SUMIFS('Trade Log'!$R$5:$R$1004,'Trade Log'!$F$5:$F$1004,$A15,'Trade Log'!$S$5:$S$1004,B$4) | C15: =SUMIFS('Trade Log'!$R$5:$R$1004,'Trade Log'!$F$5:$F$1004,$A15,'Trade Log'!$S$5:$S$1004,C$4) | D15: =SUMIFS('Trade Log'!$R$5:$R$1004,'Trade Log'!$F$5:$F$1004,$A15,'Trade Log'!$S$5:$S$1004,D$4) | E15: =SUMIFS('Trade Log'!$R$5:$R$1004,'Trade Log'!$F$5:$F$1004,$A15,'Trade Log'!$S$5:$S$1004,E$4) | F15: =SUMIFS('Trade Log'!$R$5:$R$1004,'Trade Log'!$F$5:$F$1004,$A15,'Trade Log'!$S$5:$S$1004,F$4) | G15: =SUM(B15:F15) | H15: =COUNTIFS('Trade Log'!$F$5:$F$1004,$A15,'Trade Log'!$R$5:$R$1004,"<>") | I15: =IF($H15=0,"",$G15/$H15)
A16: 46357 | B16: =SUMIFS('Trade Log'!$R$5:$R$1004,'Trade Log'!$F$5:$F$1004,$A16,'Trade Log'!$S$5:$S$1004,B$4) | C16: =SUMIFS('Trade Log'!$R$5:$R$1004,'Trade Log'!$F$5:$F$1004,$A16,'Trade Log'!$S$5:$S$1004,C$4) | D16: =SUMIFS('Trade Log'!$R$5:$R$1004,'Trade Log'!$F$5:$F$1004,$A16,'Trade Log'!$S$5:$S$1004,D$4) | E16: =SUMIFS('Trade Log'!$R$5:$R$1004,'Trade Log'!$F$5:$F$1004,$A16,'Trade Log'!$S$5:$S$1004,E$4) | F16: =SUMIFS('Trade Log'!$R$5:$R$1004,'Trade Log'!$F$5:$F$1004,$A16,'Trade Log'!$S$5:$S$1004,F$4) | G16: =SUM(B16:F16) | H16: =COUNTIFS('Trade Log'!$F$5:$F$1004,$A16,'Trade Log'!$R$5:$R$1004,"<>") | I16: =IF($H16=0,"",$G16/$H16)
... A28: 46722 | B28: =SUMIFS('Trade Log'!$R$5:$R$1004,'Trade Log'!$F$5:$F$1004,$A28,'Trade Log'!$S$5:$S$1004,B$4) | C28: =SUMIFS('Trade Log'!$R$5:$R$1004,'Trade Log'!$F$5:$F$1004,$A28,'Trade Log'!$S$5:$S$1004,C$4) | D28: =SUMIFS('Trade Log'!$R$5:$R$1004,'Trade Log'!$F$5:$F$1004,$A28,'Trade Log'!$S$5:$S$1004,D$4) | E28: =SUMIFS('Trade Log'!$R$5:$R$1004,'Trade Log'!$F$5:$F$1004,$A28,'Trade Log'!$S$5:$S$1004,E$4) | F28: =SUMIFS('Trade Log'!$R$5:$R$1004,'Trade Log'!$F$5:$F$1004,$A28,'Trade Log'!$S$5:$S$1004,F$4) | G28: =SUM(B28:F28) | H28: =COUNTIFS('Trade Log'!$F$5:$F$1004,$A28,'Trade Log'!$R$5:$R$1004,"<>") | I28: =IF($H28=0,"",$G28/$H28)
A32: Ticker | B32: Covered Call | C32: Cash Secured Put | D32: Long Option / Spread | E32: Stock Sales | F32: Other | G32: Total
A33: =IFERROR(INDEX(SORT(UNIQUE(FILTER('Trade Log'!$G$5:$G$1004,'Trade Log'!$G$5:$G$1004<>""))),ROW()-32),"") | B33: =IF($A33="","",SUMIFS('Trade Log'!$R$5:$R$1004,'Trade Log'!$G$5:$G$1004,$A33,'Trade Log'!$S$5:$S$1004,"Covered Call Premium")) | C33: =IF($A33="","",SUMIFS('Trade Log'!$R$5:$R$1004,'Trade Log'!$G$5:$G$1004,$A33,'Trade Log'!$S$5:$S$1004,"Cash Secured Put Premium")) | D33: =IF($A33="","",SUMIFS('Trade Log'!$R$5:$R$1004,'Trade Log'!$G$5:$G$1004,$A33,'Trade Log'!$S$5:$S$1004,"Long Call/Put P/L")) | E33: =IF($A33="","",SUMIFS('Trade Log'!$R$5:$R$1004,'Trade Log'!$G$5:$G$1004,$A33,'Trade Log'!$S$5:$S$1004,"Stock Sales")) | F33: =IF($A33="","",SUMIFS('Trade Log'!$R$5:$R$1004,'Trade Log'!$G$5:$G$1004,$A33,'Trade Log'!$S$5:$S$1004,"Other")) | G33: =IF($A33="","",SUM(B33:F33))
A34: =IFERROR(INDEX(SORT(UNIQUE(FILTER('Trade Log'!$G$5:$G$1004,'Trade Log'!$G$5:$G$1004<>""))),ROW()-32),"") | B34: =IF($A34="","",SUMIFS('Trade Log'!$R$5:$R$1004,'Trade Log'!$G$5:$G$1004,$A34,'Trade Log'!$S$5:$S$1004,"Covered Call Premium")) | C34: =IF($A34="","",SUMIFS('Trade Log'!$R$5:$R$1004,'Trade Log'!$G$5:$G$1004,$A34,'Trade Log'!$S$5:$S$1004,"Cash Secured Put Premium")) | D34: =IF($A34="","",SUMIFS('Trade Log'!$R$5:$R$1004,'Trade Log'!$G$5:$G$1004,$A34,'Trade Log'!$S$5:$S$1004,"Long Call/Put P/L")) | E34: =IF($A34="","",SUMIFS('Trade Log'!$R$5:$R$1004,'Trade Log'!$G$5:$G$1004,$A34,'Trade Log'!$S$5:$S$1004,"Stock Sales")) | F34: =IF($A34="","",SUMIFS('Trade Log'!$R$5:$R$1004,'Trade Log'!$G$5:$G$1004,$A34,'Trade Log'!$S$5:$S$1004,"Other")) | G34: =IF($A34="","",SUM(B34:F34))
A35: =IFERROR(INDEX(SORT(UNIQUE(FILTER('Trade Log'!$G$5:$G$1004,'Trade Log'!$G$5:$G$1004<>""))),ROW()-32),"") | B35: =IF($A35="","",SUMIFS('Trade Log'!$R$5:$R$1004,'Trade Log'!$G$5:$G$1004,$A35,'Trade Log'!$S$5:$S$1004,"Covered Call Premium")) | C35: =IF($A35="","",SUMIFS('Trade Log'!$R$5:$R$1004,'Trade Log'!$G$5:$G$1004,$A35,'Trade Log'!$S$5:$S$1004,"Cash Secured Put Premium")) | D35: =IF($A35="","",SUMIFS('Trade Log'!$R$5:$R$1004,'Trade Log'!$G$5:$G$1004,$A35,'Trade Log'!$S$5:$S$1004,"Long Call/Put P/L")) | E35: =IF($A35="","",SUMIFS('Trade Log'!$R$5:$R$1004,'Trade Log'!$G$5:$G$1004,$A35,'Trade Log'!$S$5:$S$1004,"Stock Sales")) | F35: =IF($A35="","",SUMIFS('Trade Log'!$R$5:$R$1004,'Trade Log'!$G$5:$G$1004,$A35,'Trade Log'!$S$5:$S$1004,"Other")) | G35: =IF($A35="","",SUM(B35:F35))
A36: =IFERROR(INDEX(SORT(UNIQUE(FILTER('Trade Log'!$G$5:$G$1004,'Trade Log'!$G$5:$G$1004<>""))),ROW()-32),"") | B36: =IF($A36="","",SUMIFS('Trade Log'!$R$5:$R$1004,'Trade Log'!$G$5:$G$1004,$A36,'Trade Log'!$S$5:$S$1004,"Covered Call Premium")) | C36: =IF($A36="","",SUMIFS('Trade Log'!$R$5:$R$1004,'Trade Log'!$G$5:$G$1004,$A36,'Trade Log'!$S$5:$S$1004,"Cash Secured Put Premium")) | D36: =IF($A36="","",SUMIFS('Trade Log'!$R$5:$R$1004,'Trade Log'!$G$5:$G$1004,$A36,'Trade Log'!$S$5:$S$1004,"Long Call/Put P/L")) | E36: =IF($A36="","",SUMIFS('Trade Log'!$R$5:$R$1004,'Trade Log'!$G$5:$G$1004,$A36,'Trade Log'!$S$5:$S$1004,"Stock Sales")) | F36: =IF($A36="","",SUMIFS('Trade Log'!$R$5:$R$1004,'Trade Log'!$G$5:$G$1004,$A36,'Trade Log'!$S$5:$S$1004,"Other")) | G36: =IF($A36="","",SUM(B36:F36))
A37: =IFERROR(INDEX(SORT(UNIQUE(FILTER('Trade Log'!$G$5:$G$1004,'Trade Log'!$G$5:$G$1004<>""))),ROW()-32),"") | B37: =IF($A37="","",SUMIFS('Trade Log'!$R$5:$R$1004,'Trade Log'!$G$5:$G$1004,$A37,'Trade Log'!$S$5:$S$1004,"Covered Call Premium")) | C37: =IF($A37="","",SUMIFS('Trade Log'!$R$5:$R$1004,'Trade Log'!$G$5:$G$1004,$A37,'Trade Log'!$S$5:$S$1004,"Cash Secured Put Premium")) | D37: =IF($A37="","",SUMIFS('Trade Log'!$R$5:$R$1004,'Trade Log'!$G$5:$G$1004,$A37,'Trade Log'!$S$5:$S$1004,"Long Call/Put P/L")) | E37: =IF($A37="","",SUMIFS('Trade Log'!$R$5:$R$1004,'Trade Log'!$G$5:$G$1004,$A37,'Trade Log'!$S$5:$S$1004,"Stock Sales")) | F37: =IF($A37="","",SUMIFS('Trade Log'!$R$5:$R$1004,'Trade Log'!$G$5:$G$1004,$A37,'Trade Log'!$S$5:$S$1004,"Other")) | G37: =IF($A37="","",SUM(B37:F37))
A38: =IFERROR(INDEX(SORT(UNIQUE(FILTER('Trade Log'!$G$5:$G$1004,'Trade Log'!$G$5:$G$1004<>""))),ROW()-32),"") | B38: =IF($A38="","",SUMIFS('Trade Log'!$R$5:$R$1004,'Trade Log'!$G$5:$G$1004,$A38,'Trade Log'!$S$5:$S$1004,"Covered Call Premium")) | C38: =IF($A38="","",SUMIFS('Trade Log'!$R$5:$R$1004,'Trade Log'!$G$5:$G$1004,$A38,'Trade Log'!$S$5:$S$1004,"Cash Secured Put Premium")) | D38: =IF($A38="","",SUMIFS('Trade Log'!$R$5:$R$1004,'Trade Log'!$G$5:$G$1004,$A38,'Trade Log'!$S$5:$S$1004,"Long Call/Put P/L")) | E38: =IF($A38="","",SUMIFS('Trade Log'!$R$5:$R$1004,'Trade Log'!$G$5:$G$1004,$A38,'Trade Log'!$S$5:$S$1004,"Stock Sales")) | F38: =IF($A38="","",SUMIFS('Trade Log'!$R$5:$R$1004,'Trade Log'!$G$5:$G$1004,$A38,'Trade Log'!$S$5:$S$1004,"Other")) | G38: =IF($A38="","",SUM(B38:F38))
A39: =IFERROR(INDEX(SORT(UNIQUE(FILTER('Trade Log'!$G$5:$G$1004,'Trade Log'!$G$5:$G$1004<>""))),ROW()-32),"") | B39: =IF($A39="","",SUMIFS('Trade Log'!$R$5:$R$1004,'Trade Log'!$G$5:$G$1004,$A39,'Trade Log'!$S$5:$S$1004,"Covered Call Premium")) | C39: =IF($A39="","",SUMIFS('Trade Log'!$R$5:$R$1004,'Trade Log'!$G$5:$G$1004,$A39,'Trade Log'!$S$5:$S$1004,"Cash Secured Put Premium")) | D39: =IF($A39="","",SUMIFS('Trade Log'!$R$5:$R$1004,'Trade Log'!$G$5:$G$1004,$A39,'Trade Log'!$S$5:$S$1004,"Long Call/Put P/L")) | E39: =IF($A39="","",SUMIFS('Trade Log'!$R$5:$R$1004,'Trade Log'!$G$5:$G$1004,$A39,'Trade Log'!$S$5:$S$1004,"Stock Sales")) | F39: =IF($A39="","",SUMIFS('Trade Log'!$R$5:$R$1004,'Trade Log'!$G$5:$G$1004,$A39,'Trade Log'!$S$5:$S$1004,"Other")) | G39: =IF($A39="","",SUM(B39:F39))
A40: =IFERROR(INDEX(SORT(UNIQUE(FILTER('Trade Log'!$G$5:$G$1004,'Trade Log'!$G$5:$G$1004<>""))),ROW()-32),"") | B40: =IF($A40="","",SUMIFS('Trade Log'!$R$5:$R$1004,'Trade Log'!$G$5:$G$1004,$A40,'Trade Log'!$S$5:$S$1004,"Covered Call Premium")) | C40: =IF($A40="","",SUMIFS('Trade Log'!$R$5:$R$1004,'Trade Log'!$G$5:$G$1004,$A40,'Trade Log'!$S$5:$S$1004,"Cash Secured Put Premium")) | D40: =IF($A40="","",SUMIFS('Trade Log'!$R$5:$R$1004,'Trade Log'!$G$5:$G$1004,$A40,'Trade Log'!$S$5:$S$1004,"Long Call/Put P/L")) | E40: =IF($A40="","",SUMIFS('Trade Log'!$R$5:$R$1004,'Trade Log'!$G$5:$G$1004,$A40,'Trade Log'!$S$5:$S$1004,"Stock Sales")) | F40: =IF($A40="","",SUMIFS('Trade Log'!$R$5:$R$1004,'Trade Log'!$G$5:$G$1004,$A40,'Trade Log'!$S$5:$S$1004,"Other")) | G40: =IF($A40="","",SUM(B40:F40))
A41: =IFERROR(INDEX(SORT(UNIQUE(FILTER('Trade Log'!$G$5:$G$1004,'Trade Log'!$G$5:$G$1004<>""))),ROW()-32),"") | B41: =IF($A41="","",SUMIFS('Trade Log'!$R$5:$R$1004,'Trade Log'!$G$5:$G$1004,$A41,'Trade Log'!$S$5:$S$1004,"Covered Call Premium")) | C41: =IF($A41="","",SUMIFS('Trade Log'!$R$5:$R$1004,'Trade Log'!$G$5:$G$1004,$A41,'Trade Log'!$S$5:$S$1004,"Cash Secured Put Premium")) | D41: =IF($A41="","",SUMIFS('Trade Log'!$R$5:$R$1004,'Trade Log'!$G$5:$G$1004,$A41,'Trade Log'!$S$5:$S$1004,"Long Call/Put P/L")) | E41: =IF($A41="","",SUMIFS('Trade Log'!$R$5:$R$1004,'Trade Log'!$G$5:$G$1004,$A41,'Trade Log'!$S$5:$S$1004,"Stock Sales")) | F41: =IF($A41="","",SUMIFS('Trade Log'!$R$5:$R$1004,'Trade Log'!$G$5:$G$1004,$A41,'Trade Log'!$S$5:$S$1004,"Other")) | G41: =IF($A41="","",SUM(B41:F41))
A42: =IFERROR(INDEX(SORT(UNIQUE(FILTER('Trade Log'!$G$5:$G$1004,'Trade Log'!$G$5:$G$1004<>""))),ROW()-32),"") | B42: =IF($A42="","",SUMIFS('Trade Log'!$R$5:$R$1004,'Trade Log'!$G$5:$G$1004,$A42,'Trade Log'!$S$5:$S$1004,"Covered Call Premium")) | C42: =IF($A42="","",SUMIFS('Trade Log'!$R$5:$R$1004,'Trade Log'!$G$5:$G$1004,$A42,'Trade Log'!$S$5:$S$1004,"Cash Secured Put Premium")) | D42: =IF($A42="","",SUMIFS('Trade Log'!$R$5:$R$1004,'Trade Log'!$G$5:$G$1004,$A42,'Trade Log'!$S$5:$S$1004,"Long Call/Put P/L")) | E42: =IF($A42="","",SUMIFS('Trade Log'!$R$5:$R$1004,'Trade Log'!$G$5:$G$1004,$A42,'Trade Log'!$S$5:$S$1004,"Stock Sales")) | F42: =IF($A42="","",SUMIFS('Trade Log'!$R$5:$R$1004,'Trade Log'!$G$5:$G$1004,$A42,'Trade Log'!$S$5:$S$1004,"Other")) | G42: =IF($A42="","",SUM(B42:F42))
A43: =IFERROR(INDEX(SORT(UNIQUE(FILTER('Trade Log'!$G$5:$G$1004,'Trade Log'!$G$5:$G$1004<>""))),ROW()-32),"") | B43: =IF($A43="","",SUMIFS('Trade Log'!$R$5:$R$1004,'Trade Log'!$G$5:$G$1004,$A43,'Trade Log'!$S$5:$S$1004,"Covered Call Premium")) | C43: =IF($A43="","",SUMIFS('Trade Log'!$R$5:$R$1004,'Trade Log'!$G$5:$G$1004,$A43,'Trade Log'!$S$5:$S$1004,"Cash Secured Put Premium")) | D43: =IF($A43="","",SUMIFS('Trade Log'!$R$5:$R$1004,'Trade Log'!$G$5:$G$1004,$A43,'Trade Log'!$S$5:$S$1004,"Long Call/Put P/L")) | E43: =IF($A43="","",SUMIFS('Trade Log'!$R$5:$R$1004,'Trade Log'!$G$5:$G$1004,$A43,'Trade Log'!$S$5:$S$1004,"Stock Sales")) | F43: =IF($A43="","",SUMIFS('Trade Log'!$R$5:$R$1004,'Trade Log'!$G$5:$G$1004,$A43,'Trade Log'!$S$5:$S$1004,"Other")) | G43: =IF($A43="","",SUM(B43:F43))
A44: =IFERROR(INDEX(SORT(UNIQUE(FILTER('Trade Log'!$G$5:$G$1004,'Trade Log'!$G$5:$G$1004<>""))),ROW()-32),"") | B44: =IF($A44="","",SUMIFS('Trade Log'!$R$5:$R$1004,'Trade Log'!$G$5:$G$1004,$A44,'Trade Log'!$S$5:$S$1004,"Covered Call Premium")) | C44: =IF($A44="","",SUMIFS('Trade Log'!$R$5:$R$1004,'Trade Log'!$G$5:$G$1004,$A44,'Trade Log'!$S$5:$S$1004,"Cash Secured Put Premium")) | D44: =IF($A44="","",SUMIFS('Trade Log'!$R$5:$R$1004,'Trade Log'!$G$5:$G$1004,$A44,'Trade Log'!$S$5:$S$1004,"Long Call/Put P/L")) | E44: =IF($A44="","",SUMIFS('Trade Log'!$R$5:$R$1004,'Trade Log'!$G$5:$G$1004,$A44,'Trade Log'!$S$5:$S$1004,"Stock Sales")) | F44: =IF($A44="","",SUMIFS('Trade Log'!$R$5:$R$1004,'Trade Log'!$G$5:$G$1004,$A44,'Trade Log'!$S$5:$S$1004,"Other")) | G44: =IF($A44="","",SUM(B44:F44))
... A82: =IFERROR(INDEX(SORT(UNIQUE(FILTER('Trade Log'!$G$5:$G$1004,'Trade Log'!$G$5:$G$1004<>""))),ROW()-32),"") | B82: =IF($A82="","",SUMIFS('Trade Log'!$R$5:$R$1004,'Trade Log'!$G$5:$G$1004,$A82,'Trade Log'!$S$5:$S$1004,"Covered Call Premium")) | C82: =IF($A82="","",SUMIFS('Trade Log'!$R$5:$R$1004,'Trade Log'!$G$5:$G$1004,$A82,'Trade Log'!$S$5:$S$1004,"Cash Secured Put Premium")) | D82: =IF($A82="","",SUMIFS('Trade Log'!$R$5:$R$1004,'Trade Log'!$G$5:$G$1004,$A82,'Trade Log'!$S$5:$S$1004,"Long Call/Put P/L")) | E82: =IF($A82="","",SUMIFS('Trade Log'!$R$5:$R$1004,'Trade Log'!$G$5:$G$1004,$A82,'Trade Log'!$S$5:$S$1004,"Stock Sales")) | F82: =IF($A82="","",SUMIFS('Trade Log'!$R$5:$R$1004,'Trade Log'!$G$5:$G$1004,$A82,'Trade Log'!$S$5:$S$1004,"Other")) | G82: =IF($A82="","",SUM(B82:F82))

Sheet Portfolio
A1: Portfolio Positions & Weights
A2: Current stock positions from screenshots. Weights, unrealized P/L, and option exposure update automatically.
A4: Ticker | B4: Shares | C4: Current Price | D4: Avg Cost | E4: Market Value | F4: Cost Basis | G4: Unrealized P/L | H4: Weight | I4: Open CC Contracts | J4: Open CSP Contracts | K4: Cash Secured Obligation | L4: Covered Shares | M4: Coverage % | N4: Notes
A5: CASH | B5: 5526.75 | C5: 1 | D5: 1 | E5: =IF($A5="","",IFERROR($B5*$C5,0)) | F5: =IF($A5="","",IFERROR($B5*$D5,0)) | G5: =IF($A5="","",$E5-$F5) | H5: =IF($A5="","",IFERROR($E5/SUM($E$5:$E$154),0)) | I5: =IF($A5="","",SUMIFS('Trade Log'!$M$5:$M$1004,'Trade Log'!$G$5:$G$1004,$A5,'Trade Log'!$B$5:$B$1004,"Covered Call",'Trade Log'!$C$5:$C$1004,"Open")) | J5: =IF($A5="","",SUMIFS('Trade Log'!$M$5:$M$1004,'Trade Log'!$G$5:$G$1004,$A5,'Trade Log'!$B$5:$B$1004,"Cash Secured Put",'Trade Log'!$C$5:$C$1004,"Open")) | K5: =IF($A5="","",SUMIFS('Trade Log'!$T$5:$T$1004,'Trade Log'!$G$5:$G$1004,$A5,'Trade Log'!$B$5:$B$1004,"Cash Secured Put",'Trade Log'!$C$5:$C$1004,"Open")) | L5: =IF($A5="","",$I5*100) | M5: =IFERROR($L5/$B5,0) | N5: Estimated free cash / buying power after reconciling known activity through 2026-06-09, the 2026-06-11 SHLS call purchase, and closing SONY calls. Includes the user-reported $3,000 cash addition, which was not visible as a posted deposit in the CSV exports; confirm against broker buying power.
A6: ETH | B6: 1 | C6: 2298.88 | E6: =IF($A6="","",IFERROR($B6*$C6,0)) | F6: =IF($A6="","",IFERROR($B6*$D6,0)) | G6: =IF($A6="","",$E6-$F6) | H6: =IF($A6="","",IFERROR($E6/SUM($E$5:$E$154),0)) | I6: =IF($A6="","",SUMIFS('Trade Log'!$M$5:$M$1004,'Trade Log'!$G$5:$G$1004,$A6,'Trade Log'!$B$5:$B$1004,"Covered Call",'Trade Log'!$C$5:$C$1004,"Open")) | J6: =IF($A6="","",SUMIFS('Trade Log'!$M$5:$M$1004,'Trade Log'!$G$5:$G$1004,$A6,'Trade Log'!$B$5:$B$1004,"Cash Secured Put",'Trade Log'!$C$5:$C$1004,"Open")) | K6: =IF($A6="","",SUMIFS('Trade Log'!$T$5:$T$1004,'Trade Log'!$G$5:$G$1004,$A6,'Trade Log'!$B$5:$B$1004,"Cash Secured Put",'Trade Log'!$C$5:$C$1004,"Open")) | L6: =IF($A6="","",$I6*100) | M6: =IFERROR($L6/$B6,0) | N6: 1 Ethereum token. Cost basis pending.
A7: ADEA | B7: 100 | C7: 29.69 | D7: 29.69 | E7: =IF($A7="","",IFERROR($B7*$C7,0)) | F7: =IF($A7="","",IFERROR($B7*$D7,0)) | G7: =IF($A7="","",$E7-$F7) | H7: =IF($A7="","",IFERROR($E7/SUM($E$5:$E$154),0)) | I7: =IF($A7="","",SUMIFS('Trade Log'!$M$5:$M$1004,'Trade Log'!$G$5:$G$1004,$A7,'Trade Log'!$B$5:$B$1004,"Covered Call",'Trade Log'!$C$5:$C$1004,"Open")) | J7: =IF($A7="","",SUMIFS('Trade Log'!$M$5:$M$1004,'Trade Log'!$G$5:$G$1004,$A7,'Trade Log'!$B$5:$B$1004,"Cash Secured Put",'Trade Log'!$C$5:$C$1004,"Open")) | K7: =IF($A7="","",SUMIFS('Trade Log'!$T$5:$T$1004,'Trade Log'!$G$5:$G$1004,$A7,'Trade Log'!$B$5:$B$1004,"Cash Secured Put",'Trade Log'!$C$5:$C$1004,"Open")) | L7: =IF($A7="","",$I7*100) | M7: =IFERROR($L7/$B7,0) | N7: Bought 100 shares on 2026-06-08 per joint CSV. Current price set to fill pending live quote refresh.
A8: AEHR | B8: 200 | C8: 99.84 | D8: 35.73 | E8: =IF($A8="","",IFERROR($B8*$C8,0)) | F8: =IF($A8="","",IFERROR($B8*$D8,0)) | G8: =IF($A8="","",$E8-$F8) | H8: =IF($A8="","",IFERROR($E8/SUM($E$5:$E$154),0)) | I8: =IF($A8="","",SUMIFS('Trade Log'!$M$5:$M$1004,'Trade Log'!$G$5:$G$1004,$A8,'Trade Log'!$B$5:$B$1004,"Covered Call",'Trade Log'!$C$5:$C$1004,"Open")) | J8: =IF($A8="","",SUMIFS('Trade Log'!$M$5:$M$1004,'Trade Log'!$G$5:$G$1004,$A8,'Trade Log'!$B$5:$B$1004,"Cash Secured Put",'Trade Log'!$C$5:$C$1004,"Open")) | K8: =IF($A8="","",SUMIFS('Trade Log'!$T$5:$T$1004,'Trade Log'!$G$5:$G$1004,$A8,'Trade Log'!$B$5:$B$1004,"Cash Secured Put",'Trade Log'!$C$5:$C$1004,"Open")) | L8: =IF($A8="","",$I8*100) | M8: =IFERROR($L8/$B8,0) | N8: Combined holdings from tracker plus YTD CSV activity. Price last refreshed 2026-05-28.
A9: AMD | B9: 100 | C9: 518.15 | D9: 165.46 | E9: =IF($A9="","",IFERROR($B9*$C9,0)) | F9: =IF($A9="","",IFERROR($B9*$D9,0)) | G9: =IF($A9="","",$E9-$F9) | H9: =IF($A9="","",IFERROR($E9/SUM($E$5:$E$154),0)) | I9: =IF($A9="","",SUMIFS('Trade Log'!$M$5:$M$1004,'Trade Log'!$G$5:$G$1004,$A9,'Trade Log'!$B$5:$B$1004,"Covered Call",'Trade Log'!$C$5:$C$1004,"Open")) | J9: =IF($A9="","",SUMIFS('Trade Log'!$M$5:$M$1004,'Trade Log'!$G$5:$G$1004,$A9,'Trade Log'!$B$5:$B$1004,"Cash Secured Put",'Trade Log'!$C$5:$C$1004,"Open")) | K9: =IF($A9="","",SUMIFS('Trade Log'!$T$5:$T$1004,'Trade Log'!$G$5:$G$1004,$A9,'Trade Log'!$B$5:$B$1004,"Cash Secured Put",'Trade Log'!$C$5:$C$1004,"Open")) | L9: =IF($A9="","",$I9*100) | M9: =IFERROR($L9/$B9,0) | N9: Existing pre-CSV position retained. Price last refreshed 2026-05-28.
A10: BMNR | B10: 700 | C10: 19.25 | D10: 31.58 | E10: =IF($A10="","",IFERROR($B10*$C10,0)) | F10: =IF($A10="","",IFERROR($B10*$D10,0)) | G10: =IF($A10="","",$E10-$F10) | H10: =IF($A10="","",IFERROR($E10/SUM($E$5:$E$154),0)) | I10: =IF($A10="","",SUMIFS('Trade Log'!$M$5:$M$1004,'Trade Log'!$G$5:$G$1004,$A10,'Trade Log'!$B$5:$B$1004,"Covered Call",'Trade Log'!$C$5:$C$1004,"Open")) | J10: =IF($A10="","",SUMIFS('Trade Log'!$M$5:$M$1004,'Trade Log'!$G$5:$G$1004,$A10,'Trade Log'!$B$5:$B$1004,"Cash Secured Put",'Trade Log'!$C$5:$C$1004,"Open")) | K10: =IF($A10="","",SUMIFS('Trade Log'!$T$5:$T$1004,'Trade Log'!$G$5:$G$1004,$A10,'Trade Log'!$B$5:$B$1004,"Cash Secured Put",'Trade Log'!$C$5:$C$1004,"Open")) | L10: =IF($A10="","",$I10*100) | M10: =IFERROR($L10/$B10,0) | N10: Combined across portfolios; reconciled against YTD activity. Price last refreshed 2026-05-28.
A11: CRWV | B11: 100 | C11: 102.43 | D11: 102.43 | E11: =IF($A11="","",IFERROR($B11*$C11,0)) | F11: =IF($A11="","",IFERROR($B11*$D11,0)) | G11: =IF($A11="","",$E11-$F11) | H11: =IF($A11="","",IFERROR($E11/SUM($E$5:$E$154),0)) | I11: =IF($A11="","",SUMIFS('Trade Log'!$M$5:$M$1004,'Trade Log'!$G$5:$G$1004,$A11,'Trade Log'!$B$5:$B$1004,"Covered Call",'Trade Log'!$C$5:$C$1004,"Open")) | J11: =IF($A11="","",SUMIFS('Trade Log'!$M$5:$M$1004,'Trade Log'!$G$5:$G$1004,$A11,'Trade Log'!$B$5:$B$1004,"Cash Secured Put",'Trade Log'!$C$5:$C$1004,"Open")) | K11: =IF($A11="","",SUMIFS('Trade Log'!$T$5:$T$1004,'Trade Log'!$G$5:$G$1004,$A11,'Trade Log'!$B$5:$B$1004,"Cash Secured Put",'Trade Log'!$C$5:$C$1004,"Open")) | L11: =IF($A11="","",$I11*100) | M11: =IFERROR($L11/$B11,0) | N11: Bought 50 shares at $103.07 and 50 shares at $101.79 on 2026-06-05; weighted average $102.43.
A12: FIVN | B12: 100 | C12: 23 | D12: 23 | E12: =IF($A12="","",IFERROR($B12*$C12,0)) | F12: =IF($A12="","",IFERROR($B12*$D12,0)) | G12: =IF($A12="","",$E12-$F12) | H12: =IF($A12="","",IFERROR($E12/SUM($E$5:$E$154),0)) | I12: =IF($A12="","",SUMIFS('Trade Log'!$M$5:$M$1004,'Trade Log'!$G$5:$G$1004,$A12,'Trade Log'!$B$5:$B$1004,"Covered Call",'Trade Log'!$C$5:$C$1004,"Open")) | J12: =IF($A12="","",SUMIFS('Trade Log'!$M$5:$M$1004,'Trade Log'!$G$5:$G$1004,$A12,'Trade Log'!$B$5:$B$1004,"Cash Secured Put",'Trade Log'!$C$5:$C$1004,"Open")) | K12: =IF($A12="","",SUMIFS('Trade Log'!$T$5:$T$1004,'Trade Log'!$G$5:$G$1004,$A12,'Trade Log'!$B$5:$B$1004,"Cash Secured Put",'Trade Log'!$C$5:$C$1004,"Open")) | L12: =IF($A12="","",$I12*100) | M12: =IFERROR($L12/$B12,0) | N12: Bought 100 shares on 2026-06-09 per joint CSV. Current price set to fill pending live quote refresh.
A13: HOOD | B13: 775 | C13: 84.85 | D13: 41.480645 | E13: =IF($A13="","",IFERROR($B13*$C13,0)) | F13: =IF($A13="","",IFERROR($B13*$D13,0)) | G13: =IF($A13="","",$E13-$F13) | H13: =IF($A13="","",IFERROR($E13/SUM($E$5:$E$154),0)) | I13: =IF($A13="","",SUMIFS('Trade Log'!$M$5:$M$1004,'Trade Log'!$G$5:$G$1004,$A13,'Trade Log'!$B$5:$B$1004,"Covered Call",'Trade Log'!$C$5:$C$1004,"Open")) | J13: =IF($A13="","",SUMIFS('Trade Log'!$M$5:$M$1004,'Trade Log'!$G$5:$G$1004,$A13,'Trade Log'!$B$5:$B$1004,"Cash Secured Put",'Trade Log'!$C$5:$C$1004,"Open")) | K13: =IF($A13="","",SUMIFS('Trade Log'!$T$5:$T$1004,'Trade Log'!$G$5:$G$1004,$A13,'Trade Log'!$B$5:$B$1004,"Cash Secured Put",'Trade Log'!$C$5:$C$1004,"Open")) | L13: =IF($A13="","",$I13*100) | M13: =IFERROR($L13/$B13,0) | N13: Combined across portfolios; internal transfer rows cancel in combined view. Price last refreshed 2026-05-28.
A14: NEXT | B14: 500 | C14: 8.05 | D14: 7.72 | E14: =IF($A14="","",IFERROR($B14*$C14,0)) | F14: =IF($A14="","",IFERROR($B14*$D14,0)) | G14: =IF($A14="","",$E14-$F14) | H14: =IF($A14="","",IFERROR($E14/SUM($E$5:$E$154),0)) | I14: =IF($A14="","",SUMIFS('Trade Log'!$M$5:$M$1004,'Trade Log'!$G$5:$G$1004,$A14,'Trade Log'!$B$5:$B$1004,"Covered Call",'Trade Log'!$C$5:$C$1004,"Open")) | J14: =IF($A14="","",SUMIFS('Trade Log'!$M$5:$M$1004,'Trade Log'!$G$5:$G$1004,$A14,'Trade Log'!$B$5:$B$1004,"Cash Secured Put",'Trade Log'!$C$5:$C$1004,"Open")) | K14: =IF($A14="","",SUMIFS('Trade Log'!$T$5:$T$1004,'Trade Log'!$G$5:$G$1004,$A14,'Trade Log'!$B$5:$B$1004,"Cash Secured Put",'Trade Log'!$C$5:$C$1004,"Open")) | L14: =IF($A14="","",$I14*100) | M14: =IFERROR($L14/$B14,0) | N14: Combined holdings; internal transfer rows cancel in combined view. Price last refreshed 2026-05-28.
A15: NTNX | B15: 100 | C15: 48.8 | D15: 45.35 | E15: =IF($A15="","",IFERROR($B15*$C15,0)) | F15: =IF($A15="","",IFERROR($B15*$D15,0)) | G15: =IF($A15="","",$E15-$F15) | H15: =IF($A15="","",IFERROR($E15/SUM($E$5:$E$154),0)) | I15: =IF($A15="","",SUMIFS('Trade Log'!$M$5:$M$1004,'Trade Log'!$G$5:$G$1004,$A15,'Trade Log'!$B$5:$B$1004,"Covered Call",'Trade Log'!$C$5:$C$1004,"Open")) | J15: =IF($A15="","",SUMIFS('Trade Log'!$M$5:$M$1004,'Trade Log'!$G$5:$G$1004,$A15,'Trade Log'!$B$5:$B$1004,"Cash Secured Put",'Trade Log'!$C$5:$C$1004,"Open")) | K15: =IF($A15="","",SUMIFS('Trade Log'!$T$5:$T$1004,'Trade Log'!$G$5:$G$1004,$A15,'Trade Log'!$B$5:$B$1004,"Cash Secured Put",'Trade Log'!$C$5:$C$1004,"Open")) | L15: =IF($A15="","",$I15*100) | M15: =IFERROR($L15/$B15,0) | N15: Bought 100 shares at $45.35 on 2026-05-21. Price last refreshed 2026-05-28.
A16: PLTR | B16: 770 | C16: 143.35 | D16: 18.51 | E16: =IF($A16="","",IFERROR($B16*$C16,0)) | F16: =IF($A16="","",IFERROR($B16*$D16,0)) | G16: =IF($A16="","",$E16-$F16) | H16: =IF($A16="","",IFERROR($E16/SUM($E$5:$E$154),0)) | I16: =IF($A16="","",SUMIFS('Trade Log'!$M$5:$M$1004,'Trade Log'!$G$5:$G$1004,$A16,'Trade Log'!$B$5:$B$1004,"Covered Call",'Trade Log'!$C$5:$C$1004,"Open")) | J16: =IF($A16="","",SUMIFS('Trade Log'!$M$5:$M$1004,'Trade Log'!$G$5:$G$1004,$A16,'Trade Log'!$B$5:$B$1004,"Cash Secured Put",'Trade Log'!$C$5:$C$1004,"Open")) | K16: =IF($A16="","",SUMIFS('Trade Log'!$T$5:$T$1004,'Trade Log'!$G$5:$G$1004,$A16,'Trade Log'!$B$5:$B$1004,"Cash Secured Put",'Trade Log'!$C$5:$C$1004,"Open")) | L16: =IF($A16="","",$I16*100) | M16: =IFERROR($L16/$B16,0) | N16: Combined across portfolios; reduced by 10 shares sold 2026-06-03 at $144.40 per joint CSV. Price last refreshed 2026-05-28.
A17: TSLA | B17: 29 | C17: 442.15 | D17: 172.94 | E17: =IF($A17="","",IFERROR($B17*$C17,0)) | F17: =IF($A17="","",IFERROR($B17*$D17,0)) | G17: =IF($A17="","",$E17-$F17) | H17: =IF($A17="","",IFERROR($E17/SUM($E$5:$E$154),0)) | I17: =IF($A17="","",SUMIFS('Trade Log'!$M$5:$M$1004,'Trade Log'!$G$5:$G$1004,$A17,'Trade Log'!$B$5:$B$1004,"Covered Call",'Trade Log'!$C$5:$C$1004,"Open")) | J17: =IF($A17="","",SUMIFS('Trade Log'!$M$5:$M$1004,'Trade Log'!$G$5:$G$1004,$A17,'Trade Log'!$B$5:$B$1004,"Cash Secured Put",'Trade Log'!$C$5:$C$1004,"Open")) | K17: =IF($A17="","",SUMIFS('Trade Log'!$T$5:$T$1004,'Trade Log'!$G$5:$G$1004,$A17,'Trade Log'!$B$5:$B$1004,"Cash Secured Put",'Trade Log'!$C$5:$C$1004,"Open")) | L17: =IF($A17="","",$I17*100) | M17: =IFERROR($L17/$B17,0) | N17: Existing pre-CSV position retained. Price last refreshed 2026-05-28.
E18: =IF($A18="","",IFERROR($B18*$C18,0)) | F18: =IF($A18="","",IFERROR($B18*$D18,0)) | G18: =IF($A18="","",$E18-$F18) | H18: =IF($A18="","",IFERROR($E18/SUM($E$5:$E$154),0)) | I18: =IF($A18="","",SUMIFS('Trade Log'!$M$5:$M$1004,'Trade Log'!$G$5:$G$1004,$A18,'Trade Log'!$B$5:$B$1004,"Covered Call",'Trade Log'!$C$5:$C$1004,"Open")) | J18: =IF($A18="","",SUMIFS('Trade Log'!$M$5:$M$1004,'Trade Log'!$G$5:$G$1004,$A18,'Trade Log'!$B$5:$B$1004,"Cash Secured Put",'Trade Log'!$C$5:$C$1004,"Open")) | K18: =IF($A18="","",SUMIFS('Trade Log'!$T$5:$T$1004,'Trade Log'!$G$5:$G$1004,$A18,'Trade Log'!$B$5:$B$1004,"Cash Secured Put",'Trade Log'!$C$5:$C$1004,"Open")) | L18: =IF($A18="","",$I18*100) | M18: =IFERROR($L18/$B18,0)
E19: =IF($A19="","",IFERROR($B19*$C19,0)) | F19: =IF($A19="","",IFERROR($B19*$D19,0)) | G19: =IF($A19="","",$E19-$F19) | H19: =IF($A19="","",IFERROR($E19/SUM($E$5:$E$154),0)) | I19: =IF($A19="","",SUMIFS('Trade Log'!$M$5:$M$1004,'Trade Log'!$G$5:$G$1004,$A19,'Trade Log'!$B$5:$B$1004,"Covered Call",'Trade Log'!$C$5:$C$1004,"Open")) | J19: =IF($A19="","",SUMIFS('Trade Log'!$M$5:$M$1004,'Trade Log'!$G$5:$G$1004,$A19,'Trade Log'!$B$5:$B$1004,"Cash Secured Put",'Trade Log'!$C$5:$C$1004,"Open")) | K19: =IF($A19="","",SUMIFS('Trade Log'!$T$5:$T$1004,'Trade Log'!$G$5:$G$1004,$A19,'Trade Log'!$B$5:$B$1004,"Cash Secured Put",'Trade Log'!$C$5:$C$1004,"Open")) | L19: =IF($A19="","",$I19*100) | M19: =IFERROR($L19/$B19,0)
E20: =IF($A20="","",IFERROR($B20*$C20,0)) | F20: =IF($A20="","",IFERROR($B20*$D20,0)) | G20: =IF($A20="","",$E20-$F20) | H20: =IF($A20="","",IFERROR($E20/SUM($E$5:$E$154),0)) | I20: =IF($A20="","",SUMIFS('Trade Log'!$M$5:$M$1004,'Trade Log'!$G$5:$G$1004,$A20,'Trade Log'!$B$5:$B$1004,"Covered Call",'Trade Log'!$C$5:$C$1004,"Open")) | J20: =IF($A20="","",SUMIFS('Trade Log'!$M$5:$M$1004,'Trade Log'!$G$5:$G$1004,$A20,'Trade Log'!$B$5:$B$1004,"Cash Secured Put",'Trade Log'!$C$5:$C$1004,"Open")) | K20: =IF($A20="","",SUMIFS('Trade Log'!$T$5:$T$1004,'Trade Log'!$G$5:$G$1004,$A20,'Trade Log'!$B$5:$B$1004,"Cash Secured Put",'Trade Log'!$C$5:$C$1004,"Open")) | L20: =IF($A20="","",$I20*100) | M20: =IFERROR($L20/$B20,0)
E21: =IF($A21="","",IFERROR($B21*$C21,0)) | F21: =IF($A21="","",IFERROR($B21*$D21,0)) | G21: =IF($A21="","",$E21-$F21) | H21: =IF($A21="","",IFERROR($E21/SUM($E$5:$E$154),0)) | I21: =IF($A21="","",SUMIFS('Trade Log'!$M$5:$M$1004,'Trade Log'!$G$5:$G$1004,$A21,'Trade Log'!$B$5:$B$1004,"Covered Call",'Trade Log'!$C$5:$C$1004,"Open")) | J21: =IF($A21="","",SUMIFS('Trade Log'!$M$5:$M$1004,'Trade Log'!$G$5:$G$1004,$A21,'Trade Log'!$B$5:$B$1004,"Cash Secured Put",'Trade Log'!$C$5:$C$1004,"Open")) | K21: =IF($A21="","",SUMIFS('Trade Log'!$T$5:$T$1004,'Trade Log'!$G$5:$G$1004,$A21,'Trade Log'!$B$5:$B$1004,"Cash Secured Put",'Trade Log'!$C$5:$C$1004,"Open")) | L21: =IF($A21="","",$I21*100) | M21: =IFERROR($L21/$B21,0)
E22: =IF($A22="","",IFERROR($B22*$C22,0)) | F22: =IF($A22="","",IFERROR($B22*$D22,0)) | G22: =IF($A22="","",$E22-$F22) | H22: =IF($A22="","",IFERROR($E22/SUM($E$5:$E$154),0)) | I22: =IF($A22="","",SUMIFS('Trade Log'!$M$5:$M$1004,'Trade Log'!$G$5:$G$1004,$A22,'Trade Log'!$B$5:$B$1004,"Covered Call",'Trade Log'!$C$5:$C$1004,"Open")) | J22: =IF($A22="","",SUMIFS('Trade Log'!$M$5:$M$1004,'Trade Log'!$G$5:$G$1004,$A22,'Trade Log'!$B$5:$B$1004,"Cash Secured Put",'Trade Log'!$C$5:$C$1004,"Open")) | K22: =IF($A22="","",SUMIFS('Trade Log'!$T$5:$T$1004,'Trade Log'!$G$5:$G$1004,$A22,'Trade Log'!$B$5:$B$1004,"Cash Secured Put",'Trade Log'!$C$5:$C$1004,"Open")) | L22: =IF($A22="","",$I22*100) | M22: =IFERROR($L22/$B22,0)
E23: =IF($A23="","",IFERROR($B23*$C23,0)) | F23: =IF($A23="","",IFERROR($B23*$D23,0)) | G23: =IF($A23="","",$E23-$F23) | H23: =IF($A23="","",IFERROR($E23/SUM($E$5:$E$154),0)) | I23: =IF($A23="","",SUMIFS('Trade Log'!$M$5:$M$1004,'Trade Log'!$G$5:$G$1004,$A23,'Trade Log'!$B$5:$B$1004,"Covered Call",'Trade Log'!$C$5:$C$1004,"Open")) | J23: =IF($A23="","",SUMIFS('Trade Log'!$M$5:$M$1004,'Trade Log'!$G$5:$G$1004,$A23,'Trade Log'!$B$5:$B$1004,"Cash Secured Put",'Trade Log'!$C$5:$C$1004,"Open")) | K23: =IF($A23="","",SUMIFS('Trade Log'!$T$5:$T$1004,'Trade Log'!$G$5:$G$1004,$A23,'Trade Log'!$B$5:$B$1004,"Cash Secured Put",'Trade Log'!$C$5:$C$1004,"Open")) | L23: =IF($A23="","",$I23*100) | M23: =IFERROR($L23/$B23,0)
E24: =IF($A24="","",IFERROR($B24*$C24,0)) | F24: =IF($A24="","",IFERROR($B24*$D24,0)) | G24: =IF($A24="","",$E24-$F24) | H24: =IF($A24="","",IFERROR($E24/SUM($E$5:$E$154),0)) | I24: =IF($A24="","",SUMIFS('Trade Log'!$M$5:$M$1004,'Trade Log'!$G$5:$G$1004,$A24,'Trade Log'!$B$5:$B$1004,"Covered Call",'Trade Log'!$C$5:$C$1004,"Open")) | J24: =IF($A24="","",SUMIFS('Trade Log'!$M$5:$M$1004,'Trade Log'!$G$5:$G$1004,$A24,'Trade Log'!$B$5:$B$1004,"Cash Secured Put",'Trade Log'!$C$5:$C$1004,"Open")) | K24: =IF($A24="","",SUMIFS('Trade Log'!$T$5:$T$1004,'Trade Log'!$G$5:$G$1004,$A24,'Trade Log'!$B$5:$B$1004,"Cash Secured Put",'Trade Log'!$C$5:$C$1004,"Open")) | L24: =IF($A24="","",$I24*100) | M24: =IFERROR($L24/$B24,0)
E25: =IF($A25="","",IFERROR($B25*$C25,0)) | F25: =IF($A25="","",IFERROR($B25*$D25,0)) | G25: =IF($A25="","",$E25-$F25) | H25: =IF($A25="","",IFERROR($E25/SUM($E$5:$E$154),0)) | I25: =IF($A25="","",SUMIFS('Trade Log'!$M$5:$M$1004,'Trade Log'!$G$5:$G$1004,$A25,'Trade Log'!$B$5:$B$1004,"Covered Call",'Trade Log'!$C$5:$C$1004,"Open")) | J25: =IF($A25="","",SUMIFS('Trade Log'!$M$5:$M$1004,'Trade Log'!$G$5:$G$1004,$A25,'Trade Log'!$B$5:$B$1004,"Cash Secured Put",'Trade Log'!$C$5:$C$1004,"Open")) | K25: =IF($A25="","",SUMIFS('Trade Log'!$T$5:$T$1004,'Trade Log'!$G$5:$G$1004,$A25,'Trade Log'!$B$5:$B$1004,"Cash Secured Put",'Trade Log'!$C$5:$C$1004,"Open")) | L25: =IF($A25="","",$I25*100) | M25: =IFERROR($L25/$B25,0)
E26: =IF($A26="","",IFERROR($B26*$C26,0)) | F26: =IF($A26="","",IFERROR($B26*$D26,0)) | G26: =IF($A26="","",$E26-$F26) | H26: =IF($A26="","",IFERROR($E26/SUM($E$5:$E$154),0)) | I26: =IF($A26="","",SUMIFS('Trade Log'!$M$5:$M$1004,'Trade Log'!$G$5:$G$1004,$A26,'Trade Log'!$B$5:$B$1004,"Covered Call",'Trade Log'!$C$5:$C$1004,"Open")) | J26: =IF($A26="","",SUMIFS('Trade Log'!$M$5:$M$1004,'Trade Log'!$G$5:$G$1004,$A26,'Trade Log'!$B$5:$B$1004,"Cash Secured Put",'Trade Log'!$C$5:$C$1004,"Open")) | K26: =IF($A26="","",SUMIFS('Trade Log'!$T$5:$T$1004,'Trade Log'!$G$5:$G$1004,$A26,'Trade Log'!$B$5:$B$1004,"Cash Secured Put",'Trade Log'!$C$5:$C$1004,"Open")) | L26: =IF($A26="","",$I26*100) | M26: =IFERROR($L26/$B26,0)
E27: =IF($A27="","",IFERROR($B27*$C27,0)) | F27: =IF($A27="","",IFERROR($B27*$D27,0)) | G27: =IF($A27="","",$E27-$F27) | H27: =IF($A27="","",IFERROR($E27/SUM($E$5:$E$154),0)) | I27: =IF($A27="","",SUMIFS('Trade Log'!$M$5:$M$1004,'Trade Log'!$G$5:$G$1004,$A27,'Trade Log'!$B$5:$B$1004,"Covered Call",'Trade Log'!$C$5:$C$1004,"Open")) | J27: =IF($A27="","",SUMIFS('Trade Log'!$M$5:$M$1004,'Trade Log'!$G$5:$G$1004,$A27,'Trade Log'!$B$5:$B$1004,"Cash Secured Put",'Trade Log'!$C$5:$C$1004,"Open")) | K27: =IF($A27="","",SUMIFS('Trade Log'!$T$5:$T$1004,'Trade Log'!$G$5:$G$1004,$A27,'Trade Log'!$B$5:$B$1004,"Cash Secured Put",'Trade Log'!$C$5:$C$1004,"Open")) | L27: =IF($A27="","",$I27*100) | M27: =IFERROR($L27/$B27,0)
E28: =IF($A28="","",IFERROR($B28*$C28,0)) | F28: =IF($A28="","",IFERROR($B28*$D28,0)) | G28: =IF($A28="","",$E28-$F28) | H28: =IF($A28="","",IFERROR($E28/SUM($E$5:$E$154),0)) | I28: =IF($A28="","",SUMIFS('Trade Log'!$M$5:$M$1004,'Trade Log'!$G$5:$G$1004,$A28,'Trade Log'!$B$5:$B$1004,"Covered Call",'Trade Log'!$C$5:$C$1004,"Open")) | J28: =IF($A28="","",SUMIFS('Trade Log'!$M$5:$M$1004,'Trade Log'!$G$5:$G$1004,$A28,'Trade Log'!$B$5:$B$1004,"Cash Secured Put",'Trade Log'!$C$5:$C$1004,"Open")) | K28: =IF($A28="","",SUMIFS('Trade Log'!$T$5:$T$1004,'Trade Log'!$G$5:$G$1004,$A28,'Trade Log'!$B$5:$B$1004,"Cash Secured Put",'Trade Log'!$C$5:$C$1004,"Open")) | L28: =IF($A28="","",$I28*100) | M28: =IFERROR($L28/$B28,0)
E29: =IF($A29="","",IFERROR($B29*$C29,0)) | F29: =IF($A29="","",IFERROR($B29*$D29,0)) | G29: =IF($A29="","",$E29-$F29) | H29: =IF($A29="","",IFERROR($E29/SUM($E$5:$E$154),0)) | I29: =IF($A29="","",SUMIFS('Trade Log'!$M$5:$M$1004,'Trade Log'!$G$5:$G$1004,$A29,'Trade Log'!$B$5:$B$1004,"Covered Call",'Trade Log'!$C$5:$C$1004,"Open")) | J29: =IF($A29="","",SUMIFS('Trade Log'!$M$5:$M$1004,'Trade Log'!$G$5:$G$1004,$A29,'Trade Log'!$B$5:$B$1004,"Cash Secured Put",'Trade Log'!$C$5:$C$1004,"Open")) | K29: =IF($A29="","",SUMIFS('Trade Log'!$T$5:$T$1004,'Trade Log'!$G$5:$G$1004,$A29,'Trade Log'!$B$5:$B$1004,"Cash Secured Put",'Trade Log'!$C$5:$C$1004,"Open")) | L29: =IF($A29="","",$I29*100) | M29: =IFERROR($L29/$B29,0)
... E154: =IF($A154="","",IFERROR($B154*$C154,0)) | F154: =IF($A154="","",IFERROR($B154*$D154,0)) | G154: =IF($A154="","",$E154-$F154) | H154: =IF($A154="","",IFERROR($E154/SUM($E$5:$E$154),0)) | I154: =IF($A154="","",SUMIFS('Trade Log'!$M$5:$M$1004,'Trade Log'!$G$5:$G$1004,$A154,'Trade Log'!$B$5:$B$1004,"Covered Call",'Trade Log'!$C$5:$C$1004,"Open")) | J154: =IF($A154="","",SUMIFS('Trade Log'!$M$5:$M$1004,'Trade Log'!$G$5:$G$1004,$A154,'Trade Log'!$B$5:$B$1004,"Cash Secured Put",'Trade Log'!$C$5:$C$1004,"Open")) | K154: =IF($A154="","",SUMIFS('Trade Log'!$T$5:$T$1004,'Trade Log'!$G$5:$G$1004,$A154,'Trade Log'!$B$5:$B$1004,"Cash Secured Put",'Trade Log'!$C$5:$C$1004,"Open")) | L154: =IF($A154="","",$I154*100) | M154: =IFERROR($L154/$B154,0)

Sheet Trade Ideas
A1: Trade Ideas & Recommendation Log
A2: Use this to feed examples over time: proposed setup, logic, risks, outcome, and what you want me to remember for future recommendations.
A4: Idea ID | B4: Date | C4: Ticker | D4: Market View | E4: Setup / Strategy | F4: Legs | G4: Net Credit / Debit | H4: Max Profit | I4: Max Loss | J4: Breakeven | K4: Target | L4: Status | M4: Outcome P/L | N4: Lesson / Preference | O4: Link to Trade ID

Sheet Checks
A1: Workbook Checks
A2: Quick checks for missing inputs and possible formula issues.
A4: Check | B4: Actual | C4: Expected | D4: Difference | E4: Status | F4: Notes | G4: Fix
A5: Trade rows missing ticker | B5: =COUNTIFS('Trade Log'!$A$5:$A$1004,"<>",'Trade Log'!$G$5:$G$1004,"") | C5: 0 | D5: =B5-C5 | E5: =IF(D5=0,"OK","Review") | F5: Every trade should have a ticker. | G5: Fill Trade Log ticker.
A6: Closed trades missing close date | B6: =COUNTIFS('Trade Log'!$C$5:$C$1004,"Closed",'Trade Log'!$E$5:$E$1004,"") | C6: 0 | D6: =B6-C6 | E6: =IF(D6=0,"OK","Review") | F6: Closed trades need a close date for monthly reporting. | G6: Add close date.
A7: Open CSP collateral missing | B7: =COUNTIFS('Trade Log'!$B$5:$B$1004,"Cash Secured Put",'Trade Log'!$C$5:$C$1004,"Open",'Trade Log'!$T$5:$T$1004,0) | C7: 0 | D7: =B7-C7 | E7: =IF(D7=0,"OK","Review") | F7: Open CSP rows should calculate collateral. | G7: Check strike and qty.
A8: Portfolio rows missing price | B8: =COUNTIFS(Portfolio!$A$5:$A$154,"<>",Portfolio!$C$5:$C$154,"") | C8: 0 | D8: =B8-C8 | E8: =IF(D8=0,"OK","Review") | F8: Current prices drive weights. | G8: Enter price or remove unused ticker.
A9: Overall status | B9: =COUNTIF($E$5:$E$8,"Review") | C9: 0 | D9: =B9-C9 | E9: =IF(B9=0,"OK","Review") | F9: Rolls up checks above. | G9: Resolve Review rows.

Sheet Lists
A1: Strategies | B1: Statuses | C1: Assets | D1: Actions | E1: Option Types | F1: Idea Statuses
A2: Covered Call | B2: Open | C2: Stock | D2: Buy | E2: Call | F2: Researching
A3: Cash Secured Put | B3: Closed | C3: Option | D3: Sell | E3: Put | F3: Proposed
A4: Long Call/Put | B4: Expired | C4: Option Spread | D4: Expire | F4: Entered
A5: Debit Spread | B5: Assigned | C5: Cash | D5: Assign | F5: Passed
A6: Stock Sale | B6: Rolled | F6: Closed
A7: Stock Buy | B7: Watch | F7: Archived
A8: Other
